{"src": "/home/a123456/Desktop/GetRawFeatures/binaries/dlink/DWR-935_binary/fw_upgrade", "n_num": 1, "succs": [[]], "funcaddr": 5168, "keyimportapiinfo": 3, "netkeywords": 0, "casenetkeywords": 1, "features": [[["\n", "<\\x1c\n", "\n"], [2, -31168, -32, 2, -31204, 2192, 32], 8, 23, 0, 7, 0, 2, 4, 0, []]], "fname": "_fini"}
{"src": "/home/a123456/Desktop/GetRawFeatures/binaries/dlink/DWR-935_binary/fw_upgrade", "n_num": 36, "succs": [[25, 1], [31, 2], [32, 3], [34, 4], [35, 5], [13, 6], [8], [14, 8], [7, 9], [10], [11], [12], [], [14], [30, 15], [28, 16], [22, 17], [27, 18], [19], [20], [21], [11], [29, 23], [19, 24], [21], [26], [], [20], [20], [20], [11], [26], [33], [12], [33], [10]], "funcaddr": 3016, "keyimportapiinfo": 3, "netkeywords": 0, "casenetkeywords": 1, "features": [[["\n"], [-240, 66, -26000, 64, 2, 2568, 15, 2568, 3, 2568, 11, 2568, 16, 2568, 17, 2568, 13, 2568, 2568, 18, 2, 64], 31, 70, 0, 19, 0, 2, 16, 2, ["signal", "signal", "signal", "signal", "signal", "signal", "signal", "signal", "signal", "signal", "signal", "signal", "signal", "signal", "signal", "signal", "signal", "signal", "signal", "signal", "signal", "signal", "signal", "signal"]], [["\n"], [40, 1, 64], 3, 9, 0, 2, 0, 2, 2, 2, []], [["main", "fw_upgrade", "main"], [64, 5452, 64, 6700, 5304, 58], 6, 10, 0, 4, 0, 0, 0, 1, ["fprintf"]], [["\n"], [48, 64], 4, 9, 0, 1, 0, 2, 2, 2, ["stat", "stat", "stat"]], [["main", "fw_upgrade", "main"], [64, 5492, 64, 6700, 5304, 65], 6, 12, 0, 4, 0, 2, 0, 1, ["fprintf"]], [[], [5588], 3, 9, 0, 1, 0, 0, 2, 2, ["fopen", "fopen", "fopen"]], [["[%s][%s][%s][%d]\\n[Error] Can't get size of %s\\n", "main", "main"], [64, 5540, 64, 6700, 70], 7, 10, 0, 3, 0, 0, 0, 1, ["fprintf"]], [["main", "fw_upgrade", "[%s][%s][%s][%d]\\nstop damemons before firmware upgrading\\n", "firmware_upgrade.c", "main", "/etc/init.d/stop_daemon_when_fwup.sh 2>/dev/null 1>/dev/null", "[%s][%s][%s][%d]\\nget firmware size %d\\n", "fw_upgrade", "firmware_upgrade.c", "main"], [1, 64, 6700, 64, 64, 82, 64, 5304, 5632, 5316, 64, 5692, 1, 86, 64, 5756, 5304, 5316], 27, 55, 0, 12, 0, 0, 12, 2, ["fprintf", "fprintf", "fprintf", "system", "system", "system", "sleep", "sleep", "sleep", "fprintf", "fprintf", "fprintf", "malloc", "malloc", "malloc"]], [["[%s][%s][%s][%d]\\n[Error] Can't open %s\\n", "main", "main"], [64, 5592, 64, 6700, 76], 7, 12, 0, 3, 0, 2, 0, 1, ["fprintf"]], [[], [], 1, 4, 0, 0, 0, 0, 0, 2, []], [["[%s][%s][%s][%d]\\n[Error] Can't allocate %ld bytes\\n", "fw_upgrade", "firmware_upgrade.c"], [89, 64, 5796, 5304, 5316, -1], 7, 17, 0, 5, 0, 2, 2, 1, ["fprintf", "fprintf", "fprintf"]], [[], [], 0, 3, 0, 0, 0, 2, 0, 1, []], [[], [], 0, 1, 0, 0, 0, 0, 0, 1, []], [[], [1], 2, 13, 0, 3, 0, 2, 2, 2, ["fread", "fread", "fread"]], [[], [], 0, 3, 0, 0, 0, 0, 0, 2, []], [["[%s][%s][%s][%d]\\nread firmware size %d\\n", "fw_upgrade", "firmware_upgrade.c"], [111, 64, 5904, 5304, 5316, 64, 64, 115], 15, 30, 0, 5, 0, 0, 6, 2, ["fprintf", "fprintf", "fprintf", "fclose", "fclose", "fclose", "VerifyFWCode", "VerifyFWCode", "VerifyFWCode"]], [["[%s][%s][%s][%d]\\n[Error] Can't read %ld bytes from %s\\n", "fw_upgrade", "firmware_upgrade.c"], [101, 64, 5848, 5304, 5316, -1], 11, 21, 0, 5, 0, 0, 4, 1, ["fprintf", "fprintf", "fprintf", "free", "free", "free"]], [[], [3], 2, 8, 0, 1, 0, 0, 4, 1, ["fclose", "fclose", "fclose"]], [[], [5], 0, 3, 0, 1, 0, 0, 2, 1, []], [["\n"], [240], 10, 14, 0, 1, 0, 2, 0, 0, []], [["/usr/sbin/twinkling 2>/dev/null 1>/dev/null&", "[%s][%s][%s][%d]\\nbackup restore file\\n", "fw_upgrade", "firmware_upgrade.c", "/usr/sbin/userconfig -backup /mnt/flash/config/restore.ini 2>/dev/null 1>/dev/null", "fw_upgrade", "firmware_upgrade.c", "[%s][%s][%s][%d]\\nstart firmware upgrading\\n", "[%s][%s][%s][%d]\\nfirmware upgrade done\\n", "fw_upgrade", "firmware_upgrade.c", "\n"], [64, 5992, 125, 64, 6040, 5304, 5316, 64, 6080, 127, 64, 5304, 5316, 6164, 64, 129, 6208, 5304, 5316, -2], 27, 59, 0, 15, 0, 2, 12, 2, ["system", "system", "system", "fprintf", "fprintf", "fprintf", "system", "system", "system", "fprintf", "fprintf", "fprintf", "UpgradeFWCode", "UpgradeFWCode", "UpgradeFWCode", "fprintf", "fprintf", "fprintf"]], [["[%s][%s][%s][%d]\\n[Error] VerifyFWCode failed\\n", "fw_upgrade", "firmware_upgrade.c"], [64, 5944, 5304, 5316, -1, 3], 7, 22, 0, 5, 0, 2, 6, 1, ["fprintf", "fprintf", "fprintf", "free", "free", "free"]], [[], [-1], 0, 3, 0, 1, 0, 0, 0, 2, []], [["[%s][%s][%s][%d]\\ninvalid signature\\n", "fw_upgrade", "firmware_upgrade.c"], [64, 140, 6316, 5304, 5316], 5, 11, 0, 4, 0, 2, 0, 1, ["fprintf"]], [[], [-3, 64], 1, 4, 0, 1, 0, 2, 0, 2, []], [[], [64], 1, 3, 0, 0, 0, 2, 0, 2, []], [[], [64], 1, 1, 0, 0, 0, 0, 0, 1, []], [["fw_upgrade", "firmware_upgrade.c"], [144, 6352, 5304, 5316], 4, 10, 0, 4, 0, 2, 0, 1, ["fprintf"]], [[], [148, 6392, 5304, 5316], 4, 8, 0, 4, 0, 0, 0, 1, ["fprintf"]], [[], [3], 1, 7, 0, 1, 0, 0, 4, 1, []], [[], [], 1, 7, 0, 0, 0, 2, 2, 1, ["free", "free", "free"]], [[], [64], 1, 3, 0, 0, 0, 0, 0, 2, []], [["fw_upgrade", "firmware_upgrade.c"], [136, 6276, 5304, 5316], 4, 10, 0, 4, 0, 2, 0, 1, ["fprintf"]], [["[%s][%s][%s][%d]\\nsuccess\\n", "fw_upgrade", "firmware_upgrade.c"], [132, 64, 6248, 5304, 5316, 2], 6, 18, 0, 5, 0, 2, 4, 1, ["fprintf", "fprintf", "fprintf"]], [["firmware_upgrade.c", "\n"], [64, -1, 5316, 240], 12, 20, 0, 3, 0, 2, 2, 0, []], [["fw_upgrade", "firmware_upgrade.c"], [64, 64, 5304, 5316, -1], 4, 11, 0, 3, 0, 2, 2, 1, []]], "fname": "main"}
{"src": "/home/a123456/Desktop/GetRawFeatures/binaries/dlink/DWR-935_binary/fw_upgrade", "n_num": 3, "succs": [[2, 1], [], []], "funcaddr": 2668, "keyimportapiinfo": 3, "netkeywords": 0, "casenetkeywords": 1, "features": [[["\n", "\n", "safeReboot", "\n", "[%s][%s][%s][%d]\\nupdate state = %d\\n", "fw_upgrade", "firmware_upgrade.c", "safeReboot", "\n"], [-336, 66, -26000, 64, 255, 45, 64, 64, 64, 6688, 40, 164, 64, 5336, 5304, 5316, 1, 44], 28, 50, 0, 12, 0, 2, 6, 2, ["memset", "memset", "memset", "fprintf", "fprintf", "fprintf"]], [["/var/reboot -d %d 2>/dev/null 1>/dev/null&", "fw_upgrade", "firmware_upgrade.c", "[%s][%s][%s][%d]\\nStart reboot....\\n", "\n"], [64, 5372, 170, 64, 5304, 5316, 5416, 336], 17, 35, 0, 6, 0, 2, 6, 0, ["sprintf", "sprintf", "sprintf", "system", "system", "system", "fprintf", "fprintf", "fprintf"]], [["\n"], [-1, 336], 7, 11, 0, 2, 0, 2, 0, 0, []]], "fname": "00400a6c"}
{"src": "/home/a123456/Desktop/GetRawFeatures/binaries/dlink/DWR-935_binary/fw_upgrade", "n_num": 1, "succs": [[]], "funcaddr": 1976, "keyimportapiinfo": 3, "netkeywords": 0, "casenetkeywords": 1, "features": [[["\n", "<\\x1c\n", "<\\x1c\n", "\n"], [2, -27976, -32, 2, -28012, 2404, 2, -28052, 4784, 32], 11, 35, 0, 10, 0, 2, 8, 0, []]], "fname": "_init"}
