{"src": "/home/a123456/Desktop/GetRawFeatures/binaries/belkin/bellkin_F7D4302_binary/emf", "n_num": 1, "succs": [[]], "funcaddr": 9536, "keyimportapiinfo": 2, "netkeywords": 0, "casenetkeywords": 3, "features": [[["\n", "\n"], [4032, 23616, -32, 4032, 23580, 2304, 32], 8, 25, 0, 7, 0, 2, 4, 0, []]], "fname": "_fini"}
{"src": "/home/a123456/Desktop/GetRawFeatures/binaries/belkin/bellkin_F7D4302_binary/emf", "n_num": 12, "succs": [[10, 1], [2], [7, 3], [7, 4], [9, 5], [7, 6], [9, 7], [10, 8], [2], [11], [11], []], "funcaddr": 2644, "keyimportapiinfo": 2, "netkeywords": 0, "casenetkeywords": 3, "features": [[["\n"], [4032, 30508, -48], 8, 16, 0, 3, 0, 0, 0, 2, []], [["0+@\n"], [20], 2, 4, 0, 1, 0, 0, 0, 1, []], [["\\xc0\\x0f\\x1c<Pw\\x9c'!\\xe0\\x99\\x03!(\\x80\n"], [2608], 4, 9, 0, 1, 0, 0, 2, 1, []], [["start"], [-1], 3, 9, 0, 1, 0, 0, 2, 2, ["strcmp", "strcmp", "strcmp"]], [[], [], 1, 5, 0, 0, 0, 2, 0, 2, []], [["@+@\n"], [1, 19, 16], 0, 5, 0, 3, 0, 2, 0, 2, []], [[], [], 2, 5, 0, 0, 0, 0, 0, 2, ["strcmp"]], [[], [], 1, 5, 0, 0, 0, 0, 0, 2, []], [["0+@\n", "@+@\n"], [4, 20, 31], 3, 13, 2, 2, 2, 2, 2, 1, []], [[], [], 1, 7, 0, 0, 0, 0, 2, 2, []], [[], [], 0, 3, 0, 0, 0, 2, 0, 1, []], [["\n"], [48], 6, 9, 0, 1, 0, 2, 0, 0, []]], "fname": "main"}
{"src": "/home/a123456/Desktop/GetRawFeatures/binaries/belkin/bellkin_F7D4302_binary/emf", "n_num": 17, "succs": [[2, 1], [3, 2], [6], [7, 4], [5], [6], [16], [9, 8], [5], [11, 10], [13], [14, 12], [13], [15], [16], [16], []], "funcaddr": 8352, "keyimportapiinfo": 2, "netkeywords": 0, "casenetkeywords": 3, "features": [[["\n"], [4032, 24800, -120], 10, 17, 0, 3, 0, 0, 0, 2, []], [[], [3], 0, 4, 0, 1, 0, 0, 0, 2, []], [["Invalid parameters %p %d\\n"], [11152], 4, 12, 0, 1, 0, 2, 2, 1, ["fprintf", "fprintf", "fprintf"]], [[], [16, 17], 2, 9, 0, 2, 0, 2, 2, 2, ["socket", "socket", "socket"]], [[], [-1], 1, 4, 0, 1, 0, 2, 0, 1, []], [["Netlink socket create failed\\n"], [11180], 4, 5, 0, 1, 0, 0, 0, 1, ["fputs"]], [["\n", "\n"], [32, 12, 16, 12, 44, 12, 1072], 16, 43, 0, 7, 0, 0, 10, 2, ["memset", "memset", "memset", "getpid", "getpid", "getpid", "bind", "bind", "bind", "memset", "memset", "memset", "malloc", "malloc", "malloc"]], [[], [], 0, 3, 0, 0, 0, 0, 2, 1, []], [["\n"], [120], 8, 12, 0, 1, 0, 2, 0, 0, []], [["Out of memory allocating cfg buffer\\n"], [11212], 4, 7, 0, 1, 0, 2, 0, 1, ["fputs"]], [["\n", "\n"], [1072, 16, 56, 28, 12, 24, 1], 18, 44, 0, 7, 0, 2, 8, 2, ["getpid", "getpid", "getpid", "memcpy", "memcpy", "memcpy", "memset", "memset", "memset", "sendmsg", "sendmsg", "sendmsg"]], [["sendmsg:"], [11252], 2, 5, 0, 1, 0, 2, 0, 1, ["perror"]], [[], [1072], 4, 17, 0, 1, 0, 2, 4, 2, ["memset", "memset", "memset", "recvmsg", "recvmsg", "recvmsg"]], [[], [], 2, 13, 0, 0, 0, 2, 4, 1, ["free", "free", "free"]], [["recvmsg:"], [11264], 2, 3, 0, 1, 0, 0, 0, 1, ["perror"]], [[], [], 6, 21, 0, 0, 0, 0, 6, 1, ["memcpy", "memcpy", "memcpy", "free", "free", "free", "close", "close", "close"]], [[], [], 1, 1, 0, 0, 0, 0, 0, 1, []]], "fname": "emf_cfg_request_send"}
{"src": "/home/a123456/Desktop/GetRawFeatures/binaries/belkin/bellkin_F7D4302_binary/emf", "n_num": 1, "succs": [[]], "funcaddr": 2060, "keyimportapiinfo": 2, "netkeywords": 0, "casenetkeywords": 3, "features": [[["\n", "\n"], [4032, 31092, -32, 4032, 31056, 2480, 4032, 31008, 9104, 32], 11, 39, 0, 10, 0, 2, 8, 0, []]], "fname": "_init"}
{"src": "/home/a123456/Desktop/GetRawFeatures/binaries/belkin/bellkin_F7D4302_binary/emf", "n_num": 8, "succs": [[3, 1], [7], [3], [2, 4], [6, 5], [6], [7], []], "funcaddr": 2304, "keyimportapiinfo": 2, "netkeywords": 0, "casenetkeywords": 3, "features": [[["\n"], [4032, 30848, -32], 5, 13, 0, 3, 0, 0, 0, 2, []], [[], [], 0, 3, 0, 0, 0, 2, 0, 1, []], [["\n"], [4], 3, 9, 0, 1, 0, 0, 0, 2, []], [["\n"], [32], 1, 5, 0, 1, 0, 2, 0, 0, []], [[], [], 2, 5, 0, 0, 0, 0, 2, 1, []], [[], [], 1, 5, 0, 0, 0, 0, 0, 2, []], [["\n"], [11276], 3, 8, 0, 1, 0, 0, 2, 1, []], [[], [1], 2, 3, 0, 1, 0, 0, 0, 1, []]], "fname": "00400900"}
{"src": "/home/a123456/Desktop/GetRawFeatures/binaries/belkin/bellkin_F7D4302_binary/emf", "n_num": 1, "succs": [[]], "funcaddr": 2608, "keyimportapiinfo": 2, "netkeywords": 0, "casenetkeywords": 3, "features": [[["Usage: emf  start   <bridge>\\n            stop    <bridge>\\n            status  <bridge>\\n            add     bridge  <bridge>\\n            del     bridge  <bridge>\\n            add     iface   <bridge>  <if-name>\\n            del     iface   <bridge>  <if-name>\\n            list    iface   <bridge>\\n            add     uffp    <bridge>  <if-name>\\n            del     uffp    <bridge>  <if-name>\\n            list    uffp    <bridge>\\n            add     rtport  <bridge>  <if-name>\\n            del     rtport  <bridge>  <if-name>\\n            list    rtport  <bridge>\\n            add     mfdb    <bridge>  <group-ip>  <if-name>\\n            del     mfdb    <bridge>  <group-ip>  <if-name>\\n            list    mfdb    <bridge>\\n            clear   mfdb    <bridge>\\n            show    stats   <bridge>\\n"], [4032, 30544, 9624], 3, 10, 0, 3, 0, 2, 0, 0, ["fputs", "fputs", "fputs"]]], "fname": "00400a30"}
{"src": "/home/a123456/Desktop/GetRawFeatures/binaries/belkin/bellkin_F7D4302_binary/emf", "n_num": 6, "succs": [[2, 1], [4], [5, 3], [4], [5], []], "funcaddr": 5060, "keyimportapiinfo": 2, "netkeywords": 0, "casenetkeywords": 3, "features": [[["\n", "\n", "Usage: emf  start   <bridge>\\n            stop    <bridge>\\n            status  <bridge>\\n            add     bridge  <bridge>\\n            del     bridge  <bridge>\\n            add     iface   <bridge>  <if-name>\\n            del     iface   <bridge>  <if-name>\\n            list    iface   <bridge>\\n            add     uffp    <bridge>  <if-name>\\n            del     uffp    <bridge>  <if-name>\\n            list    uffp    <bridge>\\n            add     rtport  <bridge>  <if-name>\\n            del     rtport  <bridge>  <if-name>\\n            list    rtport  <bridge>\\n            add     mfdb    <bridge>  <group-ip>  <if-name>\\n            del     mfdb    <bridge>  <group-ip>  <if-name>\\n            list    mfdb    <bridge>\\n            clear   mfdb    <bridge>\\n            show    stats   <bridge>\\n", "Unable to send request to EMF\\n"], [4032, 28092, -1096, 24, 1056, 1, 2, 1056, 10416], 18, 42, 0, 9, 0, 2, 6, 2, ["memset", "memset", "memset", "strcpy", "strcpy", "strcpy", "emf_cfg_request_send", "emf_cfg_request_send", "emf_cfg_request_send", "fputs"]], [[], [], 2, 9, 0, 0, 0, 2, 2, 1, []], [["%s\n\n", "\n"], [10796, 56], 3, 8, 0, 2, 0, 2, 0, 2, ["fprintf"]], [[], [-1], 1, 2, 0, 1, 0, 0, 0, 1, []], [[], [], 2, 6, 0, 0, 0, 0, 2, 1, []], [["\n"], [1096], 3, 7, 0, 1, 0, 2, 0, 0, []]], "fname": "004013c4"}
{"src": "/home/a123456/Desktop/GetRawFeatures/binaries/belkin/bellkin_F7D4302_binary/emf", "n_num": 6, "succs": [[2, 1], [2], [5, 3], [5, 4], [], []], "funcaddr": 2480, "keyimportapiinfo": 2, "netkeywords": 0, "casenetkeywords": 3, "features": [[["\n", "\n", "\n"], [4032, 30672, -32, 11276, 548], 7, 14, 0, 5, 0, 0, 0, 2, []], [[], [], 1, 5, 0, 0, 0, 0, 2, 1, []], [["\n"], [16], 3, 7, 0, 1, 0, 0, 0, 2, []], [[], [], 0, 3, 0, 0, 0, 0, 0, 2, []], [["\n"], [32], 1, 5, 0, 1, 0, 2, 0, 0, []], [["\n"], [32], 1, 4, 0, 1, 0, 2, 0, 0, []]], "fname": "004009b0"}
{"src": "/home/a123456/Desktop/GetRawFeatures/binaries/belkin/bellkin_F7D4302_binary/emf", "n_num": 4, "succs": [[2], [2], [1, 3], []], "funcaddr": 9104, "keyimportapiinfo": 2, "netkeywords": 0, "casenetkeywords": 3, "features": [[["\n", "\n"], [4032, 24048, -32, 4, -4], 5, 13, 0, 5, 0, 2, 0, 1, []], [[], [-1, -4], 1, 5, 0, 2, 0, 2, 0, 2, []], [[], [], 1, 4, 0, 0, 0, 0, 2, 1, []], [["\n"], [32], 2, 5, 0, 1, 0, 2, 0, 0, []]], "fname": "00402390"}
