{"src": "/home/a123456/Desktop/GetRawFeatures/binaries/asus/asus_RT-AC1200E_3.0.0.4_380_10574-gfd1b439_binary/snooper", "n_num": 1, "succs": [[]], "funcaddr": 4524, "keyimportapiinfo": 9, "netkeywords": 0, "casenetkeywords": 0, "features": [[["\n", "\n", "\n"], [2, -11580, -64, 32, 36, 35, 12, 12, 64], 21, 43, 0, 9, 0, 2, 4, 0, ["memset", "memset", "memset", "setsockopt", "setsockopt", "setsockopt"]]], "fname": "listen_query"}
{"src": "/home/a123456/Desktop/GetRawFeatures/binaries/asus/asus_RT-AC1200E_3.0.0.4_380_10574-gfd1b439_binary/snooper", "n_num": 8, "succs": [[6, 1], [3, 2], [4], [4], [7, 5], [6], [7], []], "funcaddr": 11860, "keyimportapiinfo": 9, "netkeywords": 0, "casenetkeywords": 0, "features": [[["\n"], [2, -18916, -32], 6, 14, 0, 3, 0, 0, 2, 2, ["timer_pending", "timer_pending", "timer_pending"]], [[], [], 2, 4, 0, 0, 0, 0, 0, 2, []], [[], [], 1, 1, 0, 0, 0, 0, 0, 1, []], [[], [], 1, 3, 0, 0, 0, 2, 0, 1, []], [[], [], 2, 2, 0, 0, 0, 0, 0, 1, []], [["\n"], [26212], 9, 12, 0, 1, 0, 2, 0, 2, []], [[], [], 2, 2, 0, 0, 0, 0, 0, 1, []], [["\n"], [32], 1, 5, 0, 1, 0, 2, 0, 0, []]], "fname": "del_timer"}
{"src": "/home/a123456/Desktop/GetRawFeatures/binaries/asus/asus_RT-AC1200E_3.0.0.4_380_10574-gfd1b439_binary/snooper", "n_num": 6, "succs": [[4, 1], [4, 2], [5, 3], [5], [5], []], "funcaddr": 21504, "keyimportapiinfo": 9, "netkeywords": 0, "casenetkeywords": 0, "features": [[["\n"], [2, -28560, -56, 1], 8, 16, 1, 3, 1, 0, 0, 2, []], [["\\x02\n"], [20588], 4, 9, 0, 1, 0, 2, 2, 2, []], [[], [-1], 0, 1, 0, 1, 0, 0, 0, 1, []], [["\n", "\\x03\n", "\\x02\n"], [24, 19592, 19688, 1], 8, 26, 2, 4, 2, 2, 4, 2, []], [[], [20928], 2, 9, 0, 1, 0, 2, 2, 1, []], [["\n"], [56], 5, 9, 0, 1, 0, 2, 0, 0, []]], "fname": "switch_del_portmap"}
{"src": "/home/a123456/Desktop/GetRawFeatures/binaries/asus/asus_RT-AC1200E_3.0.0.4_380_10574-gfd1b439_binary/snooper", "n_num": 23, "succs": [[6], [3, 2], [3], [5, 4], [5], [6], [1, 7], [9, 8], [9], [12], [11], [12], [20, 13], [10, 14], [11], [17, 16], [17], [19, 18], [19], [21], [21], [15, 22], []], "funcaddr": 13308, "keyimportapiinfo": 9, "netkeywords": 0, "casenetkeywords": 0, "features": [[["\n", "\n", "\\x02\n"], [2, -20364, -48, 26508, 13180], 9, 16, 0, 5, 0, 2, 0, 1, []], [[], [], 1, 5, 0, 0, 0, 0, 0, 2, []], [[], [112], 3, 9, 0, 1, 0, 0, 2, 2, ["switch_clr_portmap"]], [[], [], 2, 2, 0, 0, 0, 0, 0, 1, []], [[], [], 6, 8, 0, 0, 0, 0, 0, 2, []], [[], [], 1, 1, 0, 0, 0, 0, 0, 1, []], [[], [], 3, 9, 0, 0, 0, 0, 4, 1, ["free", "free", "free"]], [["\n"], [26776, 1], 5, 11, 1, 1, 1, 0, 2, 2, []], [["\n"], [26888], 4, 7, 0, 1, 0, 0, 2, 1, ["switch_clr_floodmap", "switch_clr_floodmap", "switch_clr_floodmap"]], [[], [], 1, 3, 0, 0, 0, 2, 0, 1, []], [[], [], 1, 3, 0, 0, 0, 0, 0, 2, []], [[], [], 3, 3, 0, 0, 0, 0, 0, 1, []], [[], [], 4, 7, 0, 0, 0, 0, 2, 1, ["free", "free", "free"]], [[], [], 1, 4, 0, 0, 0, 0, 0, 2, []], [["\n"], [26228], 0, 1, 0, 1, 0, 0, 0, 1, []], [[], [], 1, 3, 0, 0, 0, 2, 0, 1, []], [[], [], 2, 4, 0, 0, 0, 0, 0, 2, []], [[], [], 1, 1, 0, 0, 0, 0, 0, 1, []], [[], [], 1, 4, 0, 0, 0, 0, 0, 2, []], [[], [], 2, 2, 0, 0, 0, 0, 0, 1, []], [[], [], 4, 8, 0, 0, 0, 2, 2, 1, []], [[], [], 2, 5, 0, 0, 0, 0, 0, 2, ["free"]], [["\n"], [48], 5, 9, 0, 1, 0, 2, 0, 0, []]], "fname": "purge_cache"}
{"src": "/home/a123456/Desktop/GetRawFeatures/binaries/asus/asus_RT-AC1200E_3.0.0.4_380_10574-gfd1b439_binary/snooper", "n_num": 10, "succs": [[6, 1], [6, 2], [6, 3], [7], [9, 5], [8], [7], [8], [4, 9], []], "funcaddr": 21988, "keyimportapiinfo": 9, "netkeywords": 0, "casenetkeywords": 0, "features": [[["\n", "\n", "\\x03\n", "\\x02\n"], [2, -29044, -48, 24, 19592, 19688], 14, 31, 0, 6, 0, 2, 4, 2, []], [[], [], 1, 3, 0, 0, 0, 2, 0, 2, ["memcmp"]], [[], [-1], 0, 1, 0, 1, 0, 0, 0, 1, []], [[], [6], 2, 8, 0, 1, 0, 0, 2, 2, []], [[], [-1], 1, 4, 0, 1, 0, 2, 0, 1, []], [[], [1], 0, 1, 1, 0, 1, 0, 0, 1, []], [[], [1], 0, 3, 0, 1, 0, 0, 0, 2, []], [[], [1], 0, 3, 1, 0, 1, 2, 0, 1, []], [["\n"], [48], 4, 7, 0, 1, 0, 2, 0, 0, []], [[], [1], 0, 3, 1, 0, 1, 2, 0, 2, []]], "fname": "switch_get_port"}
{"src": "/home/a123456/Desktop/GetRawFeatures/binaries/asus/asus_RT-AC1200E_3.0.0.4_380_10574-gfd1b439_binary/snooper", "n_num": 19, "succs": [[2, 1], [17], [4, 3], [17], [11, 5], [12, 6], [7], [10, 8], [10, 9], [10], [7, 11], [12], [14, 13], [15, 14], [15], [18, 16], [17], [18], []], "funcaddr": 16688, "keyimportapiinfo": 9, "netkeywords": 0, "casenetkeywords": 0, "features": [[["\n"], [2, -23744, -56], 9, 19, 0, 3, 0, 0, 0, 2, []], [[], [-1], 0, 3, 0, 1, 0, 2, 0, 1, []], [["\\x02\n"], [13724, 1], 2, 9, 0, 2, 0, 0, 2, 2, []], [[], [], 0, 1, 0, 0, 0, 0, 0, 1, []], [[], [], 0, 3, 0, 0, 0, 2, 0, 1, []], [["\\x02\n"], [15376, 2], 6, 19, 0, 3, 0, 0, 4, 2, ["now", "now", "now"]], [[], [2, 1, 3], 6, 12, 2, 2, 2, 2, 0, 2, []], [[], [], 1, 1, 0, 0, 0, 0, 0, 1, []], [[], [], 0, 2, 0, 0, 0, 0, 0, 1, []], [[], [13124, 92], 5, 18, 2, 2, 2, 0, 4, 2, ["timer_pending", "timer_pending", "timer_pending"]], [[], [], 0, 3, 0, 0, 0, 2, 0, 2, []], [[], [], 1, 4, 0, 0, 0, 0, 0, 2, []], [[], [1, 9, 4], 0, 5, 0, 3, 0, 2, 0, 2, []], [[], [], 2, 2, 0, 0, 0, 0, 0, 1, []], [[], [], 2, 6, 0, 1, 0, 2, 0, 2, []], [[], [], 3, 6, 0, 0, 0, 0, 2, 1, ["mod_timer", "mod_timer", "mod_timer"]], [[], [], 0, 3, 0, 0, 0, 0, 0, 2, []], [[], [], 4, 8, 1, 0, 1, 0, 2, 1, ["switch_add_portmap", "switch_add_portmap", "switch_add_portmap"]], [["\n"], [56], 7, 10, 0, 1, 0, 2, 0, 0, []]], "fname": "add_member"}
{"src": "/home/a123456/Desktop/GetRawFeatures/binaries/asus/asus_RT-AC1200E_3.0.0.4_380_10574-gfd1b439_binary/snooper", "n_num": 1, "succs": [[]], "funcaddr": 24688, "keyimportapiinfo": 9, "netkeywords": 0, "casenetkeywords": 0, "features": [[["\n", "\\x02\n", "\n"], [2, -31744, -32, 2, -31780, 4176, 32], 8, 23, 0, 7, 0, 2, 4, 0, []]], "fname": "_fini"}
{"src": "/home/a123456/Desktop/GetRawFeatures/binaries/asus/asus_RT-AC1200E_3.0.0.4_380_10574-gfd1b439_binary/snooper", "n_num": 4, "succs": [[3, 1], [3, 2], [3], []], "funcaddr": 21332, "keyimportapiinfo": 9, "netkeywords": 0, "casenetkeywords": 0, "features": [[["\n"], [2, -28388, -48, 1, -1], 7, 14, 1, 4, 1, 0, 0, 2, []], [["\n", "\\x03\n", "\\x02\n"], [24, 19592, 19688, 1], 6, 19, 0, 4, 0, 2, 4, 2, []], [["\n"], [48], 4, 8, 0, 1, 0, 2, 0, 0, []], [["\\x02\n"], [20928, -1], 3, 8, 0, 2, 0, 0, 2, 1, []]], "fname": "switch_clr_portmap"}
{"src": "/home/a123456/Desktop/GetRawFeatures/binaries/asus/asus_RT-AC1200E_3.0.0.4_380_10574-gfd1b439_binary/snooper", "n_num": 11, "succs": [[9, 1], [9, 2], [9, 3], [5, 4], [6], [6], [8, 7], [8], [10], [10], []], "funcaddr": 10888, "keyimportapiinfo": 9, "netkeywords": 0, "casenetkeywords": 0, "features": [[["\n", "\n", "\n"], [2, -17944, -48, -20], 10, 25, 0, 5, 0, 0, 2, 2, ["memset", "memset", "memset"]], [["$\\x10\n", "!\\xa0\\xc0\n", "\n", "\n"], [-241, 64, -64, 1, 2, 20, -4], 13, 26, 2, 6, 2, 0, 2, 2, ["random", "random", "random"]], [[], [-1], 0, 1, 0, 1, 0, 0, 0, 1, []], [["\\x10\n", "$\\x10C\n", "\n", "\n"], [4, -16, -108, 6, 26176, 8, 12, 2, 17], 6, 24, 3, 10, 3, 0, 0, 2, []], [[], [100], 2, 6, 0, 1, 0, 0, 0, 2, []], [[], [], 0, 3, 0, 0, 0, 2, 0, 1, []], [[], [10], 0, 2, 0, 1, 0, 0, 0, 1, []], [[], [3], 5, 8, 0, 1, 0, 2, 0, 2, []], [[], [248, 2, 125], 4, 7, 2, 1, 2, 0, 0, 1, []], [[], [8416, 65535, 255, 8, 8], 4, 24, 5, 3, 5, 2, 4, 1, []], [["\n"], [48], 6, 10, 0, 1, 0, 2, 0, 0, []]], "fname": "build_query"}
{"src": "/home/a123456/Desktop/GetRawFeatures/binaries/asus/asus_RT-AC1200E_3.0.0.4_380_10574-gfd1b439_binary/snooper", "n_num": 105, "succs": [[13], [14, 2], [15, 3], [11, 4], [14, 5], [15, 6], [10, 7], [12, 8], [19, 9], [16], [16], [16], [13], [17], [16], [16], [17], [1, 18], [20, 19], [104], [22, 21], [22], [24, 23], [24], [26, 25], [27], [27], [29, 28], [104], [31, 30], [104], [54, 32], [39, 33], [41, 34], [36, 35], [53], [38, 37], [53], [40, 39], [53], [42, 41], [53], [44, 43], [53], [46, 45], [53], [48, 47], [53], [50, 49], [51], [51], [55, 52], [100], [54], [104], [99, 56], [58, 57], [98], [60, 59], [97], [64, 61], [63, 62], [63], [64], [93], [66], [66, 67], [70, 68], [93, 69], [86], [91, 71], [79, 72], [75, 73], [72, 74], [85, 75], [79, 76], [79, 77], [96, 78], [79], [91, 80], [81], [87, 82], [81, 83], [88, 84], [85], [86], [95], [88], [92, 89], [91, 90], [96, 91], [92], [93], [65, 94], [95], [96], [97], [98], [100], [100], [102, 101], [102], [104, 103], [104], []], "funcaddr": 4996, "keyimportapiinfo": 9, "netkeywords": 0, "casenetkeywords": 0, "features": [[["\n", "\n", "s:b:v:qQdDxh", "\n"], [2, -12052, -1976, 47, 1, 1, 24852, -1], 21, 39, 0, 8, 0, 2, 2, 1, ["strrchr", "strrchr", "strrchr"]], [[], [], 1, 3, 0, 0, 0, 2, 0, 1, ["getopt"]], [[], [68, 81], 0, 4, 0, 2, 0, 2, 0, 2, []], [[], [98], 0, 3, 0, 1, 0, 2, 0, 2, []], [[], [100], 1, 5, 1, 0, 1, 2, 0, 1, []], [[], [100], 0, 3, 0, 1, 0, 2, 0, 2, []], [[], [113], 1, 3, 1, 0, 1, 0, 0, 1, []], [[], [113], 0, 3, 0, 1, 0, 2, 0, 2, []], [[], [], 1, 3, 0, 0, 0, 2, 0, 1, []], [[], [115], 0, 3, 0, 1, 0, 2, 0, 2, []], [[], [118], 0, 3, 0, 1, 0, 2, 0, 2, []], [[], [120], 0, 3, 0, 1, 0, 2, 0, 2, []], [[], [], 1, 3, 0, 0, 0, 2, 0, 1, []], [[], [], 1, 3, 0, 0, 0, 2, 0, 2, []], [[], [], 4, 6, 0, 0, 0, 0, 2, 1, ["atoi", "atoi", "atoi"]], [[], [], 1, 3, 0, 0, 0, 2, 0, 1, []], [["\\x18\n"], [4492, 1], 3, 10, 0, 2, 0, 2, 2, 1, []], [[], [], 1, 1, 0, 0, 0, 0, 0, 1, ["getopt"]], [["s:b:v:qQdDxh"], [], 1, 9, 0, 0, 0, 2, 2, 2, []], [[], [], 1, 3, 0, 0, 0, 0, 0, 2, []], [[], [], 1, 3, 0, 0, 0, 0, 0, 2, ["strcmp"]], [["\n"], [1976], 10, 14, 0, 1, 0, 2, 0, 0, []], [[], [], 1, 6, 0, 0, 0, 0, 2, 1, []], [[], [], 2, 4, 0, 0, 0, 0, 0, 2, ["openlog"]], [[], [1, 24], 1, 6, 0, 2, 0, 0, 2, 1, []], [[], [], 1, 3, 0, 0, 0, 0, 0, 2, []], [["\n"], [25408], 1, 5, 0, 1, 0, 2, 0, 1, []], [["@\n"], [24868], 0, 2, 0, 1, 0, 0, 0, 1, []], [["started on %s%s%s"], [24872, 6, 24000, 1], 10, 23, 0, 4, 0, 0, 4, 2, ["logger", "logger", "logger", "if_nametoindex", "if_nametoindex", "if_nametoindex"]], [["ifindex: %s"], [-1, 24892, 3], 8, 21, 0, 3, 0, 2, 6, 1, ["__errno_location", "__errno_location", "__errno_location", "strerror", "strerror", "strerror", "logger", "logger", "logger"]], [[], [17, 1, 8], 4, 11, 0, 3, 0, 2, 2, 2, ["open_socket", "open_socket", "open_socket"]], [[], [-1], 0, 3, 0, 1, 0, 2, 0, 1, []], [[], [2, 3, 2], 4, 11, 0, 3, 0, 2, 2, 2, ["open_socket", "open_socket", "open_socket"]], [["\\x06\n"], [8, 25644, 65535, 26], 5, 13, 1, 3, 1, 2, 2, 2, ["setsockopt", "setsockopt", "setsockopt"]], [[], [-1, -1], 5, 11, 0, 2, 0, 2, 2, 1, ["close", "close", "close"]], [["\n"], [36, 4, 65535, 4098], 4, 13, 1, 3, 1, 2, 2, 2, ["setsockopt", "setsockopt", "setsockopt"]], [["setsockopt::SO_ATTACH_FILTER: %s"], [24904], 7, 15, 0, 1, 0, 2, 4, 1, ["__errno_location", "__errno_location", "__errno_location", "strerror", "strerror", "strerror", "logger"]], [["\n"], [128, 20, 17, 20], 9, 22, 0, 4, 0, 2, 4, 2, ["memset", "memset", "memset", "bind", "bind", "bind"]], [["setsockopt::SO_RCVBUF: %s"], [24940], 7, 15, 0, 1, 0, 2, 4, 1, ["__errno_location", "__errno_location", "__errno_location", "strerror", "strerror", "strerror", "logger"]], [["bind: %s"], [24968], 7, 15, 0, 1, 0, 2, 4, 1, ["__errno_location", "__errno_location", "__errno_location", "strerror", "strerror", "strerror", "logger"]], [["\n"], [60, 16, 2, 16, 263, 1], 9, 24, 0, 6, 0, 2, 4, 2, ["memset", "memset", "memset", "setsockopt", "setsockopt", "setsockopt"]], [[], [3, -1], 6, 13, 0, 2, 0, 0, 4, 1, ["close", "close", "close"]], [["setsockopt::PACKET_ADD_MEMBERSHIP: %s"], [24980], 7, 15, 0, 1, 0, 2, 4, 1, ["__errno_location", "__errno_location", "__errno_location", "strerror", "strerror", "strerror", "logger"]], [["\\x06\n"], [25636, 65535, 26], 5, 12, 1, 2, 1, 2, 2, 2, ["setsockopt", "setsockopt", "setsockopt"]], [[], [65535, 4098], 4, 11, 1, 1, 1, 2, 2, 2, ["setsockopt", "setsockopt", "setsockopt"]], [[], [65535, 25], 6, 16, 1, 1, 1, 2, 4, 2, ["strlen", "strlen", "strlen", "setsockopt", "setsockopt", "setsockopt"]], [["setsockopt::SO_BINDTODEVICE: %s"], [25020], 7, 15, 0, 1, 0, 2, 4, 1, ["__errno_location", "__errno_location", "__errno_location", "strerror", "strerror", "strerror", "logger"]], [["\n"], [34, 40], 4, 11, 0, 2, 0, 2, 2, 2, ["setsockopt", "setsockopt", "setsockopt"]], [["setsockopt::IP_MULTICAST_LOOP: %s"], [25052], 7, 15, 0, 1, 0, 2, 4, 1, ["__errno_location", "__errno_location", "__errno_location", "strerror", "strerror", "strerror", "logger"]], [["\n"], [96, 32, 16, 35111], 7, 24, 1, 3, 1, 2, 6, 2, ["memset", "memset", "memset", "strncpy", "strncpy", "strncpy", "ioctl", "ioctl", "ioctl"]], [["ioctl::SIOCGIFHWADDR: %s"], [25088], 7, 15, 0, 1, 0, 2, 4, 1, ["__errno_location", "__errno_location", "__errno_location", "strerror", "strerror", "strerror", "logger"]], [["\n"], [114, 32, 16, 35093], 12, 30, 1, 3, 1, 2, 6, 2, ["memset", "memset", "memset", "strncpy", "strncpy", "strncpy", "ioctl", "ioctl", "ioctl"]], [[], [], 0, 3, 0, 0, 0, 2, 0, 1, []], [[], [], 1, 1, 0, 0, 0, 0, 0, 1, []], [[], [], 4, 8, 0, 0, 0, 2, 2, 2, ["switch_probe", "switch_probe", "switch_probe"]], [[], [-1], 0, 3, 0, 1, 0, 2, 0, 1, []], [[], [], 4, 9, 0, 0, 0, 2, 2, 2, ["switch_init", "switch_init", "switch_init"]], [[], [], 3, 5, 0, 0, 0, 2, 0, 2, ["close"]], [[], [], 2, 7, 0, 0, 0, 2, 2, 2, ["init_timers", "init_timers", "init_timers"]], [[], [-1], 0, 1, 0, 1, 0, 0, 0, 1, []], [[], [-1], 0, 3, 0, 1, 0, 2, 0, 1, []], [[], [], 2, 7, 0, 0, 0, 2, 2, 2, ["init_cache", "init_cache", "init_cache"]], [[], [], 2, 7, 0, 0, 0, 2, 2, 1, ["switch_done", "switch_done", "switch_done"]], [[], [-1], 0, 3, 0, 1, 0, 2, 0, 1, []], [[], [], 2, 4, 0, 0, 0, 0, 0, 2, []], [[], [], 2, 5, 0, 0, 0, 0, 2, 1, ["purge_timers", "purge_timers", "purge_timers"]], [[], [], 2, 8, 0, 0, 0, 2, 2, 2, ["daemon", "daemon", "daemon"]], [["\\x08\n", "\n", "\n", "\n", "\n", "\n", "\n", "\n", "\n", "\n", "\n"], [4432, 264, 256, 15, 2, 14, 128, 76, 88, 36, 32, 60, 400, 44], 19, 51, 0, 14, 0, 2, 10, 1, ["sigemptyset", "sigemptyset", "sigemptyset", "sigaction", "sigaction", "sigaction", "sigaction", "sigaction", "sigaction", "sigaction", "sigaction", "sigaction", "init_querier", "init_querier", "init_querier"]], [["daemon: %s"], [25116, 3], 8, 18, 0, 2, 0, 0, 6, 1, ["__errno_location", "__errno_location", "__errno_location", "strerror", "strerror", "strerror", "logger", "logger", "logger"]], [[], [], 1, 1, 0, 0, 0, 0, 0, 1, []], [[], [], 3, 5, 0, 0, 0, 0, 0, 2, []], [[], [], 1, 2, 0, 0, 0, 0, 0, 1, []], [["\n"], [4, 1], 2, 6, 0, 2, 0, 2, 0, 2, []], [["\n", "\n"], [5, 2, 5, 2, 1], 9, 37, 8, 3, 8, 2, 4, 2, ["next_timer", "next_timer", "next_timer", "select", "select", "select"]], [[], [4], 3, 9, 0, 1, 0, 2, 2, 2, ["__errno_location", "__errno_location", "__errno_location"]], [[], [], 1, 3, 0, 0, 0, 0, 0, 2, []], [["select: %s"], [25128], 4, 10, 0, 1, 0, 2, 2, 1, ["strerror", "strerror", "strerror", "logger"]], [[], [3], 0, 4, 0, 1, 0, 2, 0, 1, []], [["\n"], [5, 2, 1], 2, 9, 4, 1, 4, 0, 0, 2, []], [[], [], 1, 1, 0, 0, 0, 0, 0, 1, ["run_timers"]], [[], [20, 1500], 8, 17, 0, 2, 0, 2, 2, 2, ["recvfrom", "recvfrom", "recvfrom", "__errno_location"]], [["\n"], [5, 2, 1, 16], 1, 9, 4, 2, 4, 0, 0, 2, []], [[], [4], 2, 8, 0, 1, 0, 2, 2, 2, []], [[], [65280, 65535, 1536, 1], 4, 9, 3, 0, 3, 2, 0, 2, []], [[], [127], 1, 4, 0, 1, 0, 2, 0, 2, ["strerror"]], [["recvfrom: %s"], [25140], 3, 7, 0, 1, 0, 0, 2, 1, ["logger"]], [[], [], 1, 3, 0, 0, 0, 2, 0, 2, ["accept_igmp"]], [[], [], 2, 9, 0, 0, 0, 2, 2, 2, []], [[], [], 1, 1, 0, 0, 0, 0, 0, 1, []], [[], [], 2, 5, 0, 0, 0, 0, 2, 1, ["purge_cache", "purge_cache", "purge_cache"]], [[], [], 1, 1, 0, 0, 0, 0, 0, 1, []], [[], [1500], 7, 15, 0, 1, 0, 2, 2, 2, ["recvfrom", "recvfrom", "recvfrom", "__errno_location"]], [[], [4], 2, 8, 0, 1, 0, 2, 2, 2, []], [[], [], 0, 1, 0, 0, 0, 0, 0, 1, []], [[], [127], 0, 4, 0, 1, 0, 2, 0, 2, []], [[], [], 1, 1, 0, 0, 0, 0, 0, 1, ["strerror"]], [[], [2], 1, 4, 0, 1, 0, 2, 0, 2, ["run_timers"]], [[], [], 1, 4, 0, 0, 0, 0, 2, 1, []], [[], [], 1, 3, 0, 0, 0, 2, 0, 2, ["accept_igmp"]], [[], [], 1, 4, 0, 0, 0, 0, 2, 1, []], [[], [1], 2, 9, 0, 1, 0, 2, 2, 2, []], [["terminated with signal %d"], [25156, 6], 2, 5, 0, 2, 0, 0, 0, 1, ["logger"]], [[], [], 1, 4, 0, 0, 0, 0, 2, 1, []], [[], [], 3, 5, 0, 0, 0, 2, 0, 2, ["close"]], [[], [], 1, 4, 0, 0, 0, 0, 2, 1, []]], "fname": "main"}
{"src": "/home/a123456/Desktop/GetRawFeatures/binaries/asus/asus_RT-AC1200E_3.0.0.4_380_10574-gfd1b439_binary/snooper", "n_num": 33, "succs": [[3], [25, 2], [3], [1, 4], [8, 5], [7, 6], [7], [8], [22, 9], [12], [14, 11], [12], [10, 13], [28], [16, 15], [16], [19, 17], [21, 18], [21], [21, 20], [21], [22], [24, 23], [24], [27, 25], [28, 26], [32], [28], [32, 29], [32, 30], [32, 31], [32], []], "funcaddr": 17144, "keyimportapiinfo": 9, "netkeywords": 0, "casenetkeywords": 0, "features": [[["\n", "\n", "\n"], [2, -24200, -56, 63, 2, 26236], 14, 30, 2, 5, 2, 2, 4, 1, ["now", "now", "now", "ether_hash", "ether_hash", "ether_hash"]], [[], [20, 6], 3, 8, 0, 2, 0, 0, 0, 2, ["memcmp"]], [[], [], 1, 6, 0, 0, 0, 0, 2, 2, []], [[], [], 1, 1, 0, 0, 0, 0, 0, 1, []], [[], [], 2, 5, 0, 1, 0, 2, 0, 2, ["switch_get_port"]], [["\n"], [26228], 3, 7, 0, 1, 0, 0, 0, 2, []], [[], [1, 28], 3, 9, 0, 2, 0, 0, 2, 2, ["calloc", "calloc", "calloc"]], [[], [], 1, 3, 0, 0, 0, 0, 0, 2, []], [[], [1], 2, 3, 0, 1, 0, 0, 0, 1, []], [[], [], 1, 1, 0, 0, 0, 0, 0, 1, []], [[], [], 1, 4, 0, 0, 0, 2, 0, 1, []], [[], [20], 11, 14, 0, 1, 0, 0, 0, 2, []], [[], [], 3, 5, 0, 0, 0, 0, 0, 2, ["switch_get_port"]], [[], [], 1, 5, 0, 1, 0, 2, 0, 2, []], [[], [], 1, 2, 0, 0, 0, 0, 0, 1, []], [[], [], 2, 4, 0, 0, 0, 0, 0, 2, []], [[], [], 0, 3, 0, 0, 0, 2, 0, 1, []], [[], [], 1, 7, 0, 0, 0, 0, 2, 2, []], [[], [], 3, 3, 0, 0, 0, 0, 0, 1, []], [[], [], 3, 5, 0, 0, 0, 0, 0, 2, []], [[], [], 3, 5, 0, 0, 0, 0, 0, 2, []], [[], [], 4, 6, 0, 0, 0, 0, 0, 2, []], [[], [], 2, 4, 0, 0, 0, 2, 0, 1, []], [["\n"], [24, 28], 2, 7, 0, 2, 0, 0, 2, 1, ["memset", "memset", "memset"]], [["\n"], [26228], 1, 2, 0, 1, 0, 0, 0, 1, []], [[], [4], 3, 4, 0, 1, 0, 0, 0, 1, []], [["\n"], [26228], 11, 14, 0, 1, 0, 0, 0, 2, []], [[], [], 1, 1, 0, 0, 0, 0, 0, 1, ["switch_get_port"]], [[], [], 1, 3, 0, 0, 0, 2, 0, 1, []], [["\n"], [56], 6, 10, 0, 1, 0, 2, 0, 0, []], [[], [], 0, 3, 0, 0, 0, 2, 0, 2, []], [[], [3000], 0, 3, 0, 1, 0, 0, 0, 2, []], [[], [], 2, 2, 0, 0, 0, 0, 0, 1, []]], "fname": "get_port"}
{"src": "/home/a123456/Desktop/GetRawFeatures/binaries/asus/asus_RT-AC1200E_3.0.0.4_380_10574-gfd1b439_binary/snooper", "n_num": 1, "succs": [[]], "funcaddr": 18388, "keyimportapiinfo": 9, "netkeywords": 0, "casenetkeywords": 0, "features": [[["\n", "\n", "\n"], [2, -25444, -40, 48, 40], 9, 20, 0, 5, 0, 2, 2, 0, ["vsyslog", "vsyslog", "vsyslog"]]], "fname": "logger"}
{"src": "/home/a123456/Desktop/GetRawFeatures/binaries/asus/asus_RT-AC1200E_3.0.0.4_380_10574-gfd1b439_binary/snooper", "n_num": 21, "succs": [[19, 1], [3, 2], [20, 3], [7, 4], [6, 5], [7, 6], [7], [12, 8], [13, 9], [11, 10], [16], [12], [13], [16, 14], [16, 15], [16], [20, 17], [19, 18], [20], [20], []], "funcaddr": 9660, "keyimportapiinfo": 9, "netkeywords": 0, "casenetkeywords": 0, "features": [[["\n"], [2, -16716, -64], 10, 19, 0, 3, 0, 2, 0, 2, []], [[], [61440], 1, 3, 0, 0, 0, 0, 0, 2, []], [[], [], 0, 1, 0, 0, 0, 0, 0, 1, []], [[], [24, 57344], 1, 6, 2, 0, 2, 2, 0, 2, []], [[], [], 1, 3, 0, 0, 0, 0, 0, 2, []], [["\n"], [64], 7, 10, 0, 1, 0, 2, 0, 0, []], [[], [], 2, 5, 0, 0, 0, 0, 0, 2, []], [[], [1], 2, 5, 1, 0, 1, 0, 0, 2, []], [[], [], 1, 3, 0, 0, 0, 0, 0, 2, []], [["\n"], [-2, 3, 58392, 26192], 10, 19, 2, 3, 2, 0, 4, 1, ["now", "now", "now", "mod_timer", "mod_timer", "mod_timer"]], [[], [], 1, 3, 0, 0, 0, 0, 0, 2, []], [[], [], 1, 1, 0, 0, 0, 0, 0, 1, []], [["\\x02\n"], [8928], 2, 8, 0, 1, 0, 0, 2, 2, []], [[], [1], 0, 4, 1, 0, 1, 0, 0, 2, []], [["\n"], [24], 4, 15, 0, 1, 0, 2, 4, 1, ["ether_mtoe", "ether_mtoe", "ether_mtoe", "expire_members", "expire_members", "expire_members"]], [[], [], 1, 1, 0, 0, 0, 0, 0, 1, []], [[], [1], 0, 3, 0, 1, 0, 0, 0, 2, []], [["\n"], [26176], 0, 3, 0, 1, 0, 0, 0, 2, []], [[], [], 1, 1, 0, 0, 0, 0, 0, 1, []], [[], [], 2, 7, 0, 0, 0, 2, 2, 2, ["get_port", "get_port", "get_port"]], [[], [3, 58392, 1], 3, 11, 1, 1, 1, 2, 2, 1, ["add_router", "add_router", "add_router"]]], "fname": "accept_query"}
{"src": "/home/a123456/Desktop/GetRawFeatures/binaries/asus/asus_RT-AC1200E_3.0.0.4_380_10574-gfd1b439_binary/snooper", "n_num": 6, "succs": [[4, 1], [4, 2], [5, 3], [5], [5], []], "funcaddr": 21748, "keyimportapiinfo": 9, "netkeywords": 0, "casenetkeywords": 0, "features": [[["\n"], [2, -28804, -56, 1], 8, 16, 1, 3, 1, 0, 0, 2, []], [["\\x02\n"], [20588], 4, 9, 0, 1, 0, 2, 2, 2, []], [[], [-1], 0, 1, 0, 1, 0, 0, 0, 1, []], [["\n", "\\x03\n", "\\x02\n"], [24, 19592, 19688, 1], 8, 25, 2, 4, 2, 2, 4, 2, []], [[], [20928], 2, 9, 0, 1, 0, 2, 2, 1, []], [["\n"], [56], 5, 9, 0, 1, 0, 2, 0, 0, []]], "fname": "switch_add_portmap"}
{"src": "/home/a123456/Desktop/GetRawFeatures/binaries/asus/asus_RT-AC1200E_3.0.0.4_380_10574-gfd1b439_binary/snooper", "n_num": 16, "succs": [[14, 1], [14, 2], [10, 3], [5, 4], [15], [7, 6], [8], [8], [11, 9], [10], [11], [13, 12], [13], [15], [15], []], "funcaddr": 11604, "keyimportapiinfo": 9, "netkeywords": 0, "casenetkeywords": 0, "features": [[["\n"], [2, -18660, -40], 5, 12, 0, 3, 0, 0, 0, 2, []], [[], [], 2, 4, 0, 0, 0, 0, 0, 2, ["timer_pending"]], [[], [-1], 0, 1, 0, 1, 0, 0, 0, 1, []], [[], [], 1, 7, 0, 0, 0, 0, 2, 2, []], [[], [], 1, 4, 0, 0, 0, 2, 0, 2, []], [[], [], 1, 1, 0, 0, 0, 0, 0, 1, []], [[], [1], 0, 3, 0, 1, 0, 2, 0, 1, []], [[], [], 2, 4, 0, 0, 0, 0, 0, 2, []], [["\n"], [40], 3, 7, 0, 1, 0, 2, 0, 0, []], [[], [], 1, 3, 0, 0, 0, 2, 0, 1, []], [[], [], 2, 2, 0, 0, 0, 0, 0, 1, []], [["\n"], [26212], 7, 10, 0, 1, 0, 2, 0, 2, []], [[], [], 2, 2, 0, 0, 0, 0, 0, 1, []], [["\n"], [26212], 2, 7, 0, 2, 0, 2, 0, 2, []], [[], [], 1, 1, 0, 0, 0, 0, 0, 1, []], [[], [], 6, 8, 0, 0, 0, 2, 0, 1, []]], "fname": "mod_timer"}
{"src": "/home/a123456/Desktop/GetRawFeatures/binaries/asus/asus_RT-AC1200E_3.0.0.4_380_10574-gfd1b439_binary/snooper", "n_num": 18, "succs": [[2, 1], [17], [4, 3], [4], [6, 5], [7, 6], [7], [17, 8], [12, 9], [11, 10], [11], [12], [16], [15, 14], [15], [16], [13, 17], []], "funcaddr": 15804, "keyimportapiinfo": 9, "netkeywords": 0, "casenetkeywords": 0, "features": [[["\n"], [2, -22860, -48], 8, 17, 0, 3, 0, 0, 0, 2, []], [[], [-1], 0, 3, 0, 1, 0, 2, 0, 1, []], [["\n", "\\x02\n"], [26776, 1, 15376], 7, 21, 0, 4, 0, 0, 4, 2, ["now", "now", "now"]], [["\n"], [48], 6, 10, 0, 1, 0, 2, 0, 0, []], [["\n"], [2], 3, 5, 1, 1, 1, 0, 0, 1, []], [["!\\x18\n", "\n"], [13124, 26868], 6, 17, 1, 2, 1, 0, 4, 2, ["timer_pending", "timer_pending", "timer_pending"]], [[], [], 2, 6, 0, 1, 0, 2, 0, 2, []], [["\n"], [26868], 3, 6, 0, 1, 0, 0, 2, 1, ["mod_timer", "mod_timer", "mod_timer"]], [[], [], 1, 3, 0, 0, 0, 0, 0, 2, []], [[], [1], 2, 5, 1, 0, 1, 0, 0, 2, []], [["\n"], [26888], 5, 11, 0, 1, 0, 2, 2, 2, ["switch_set_floodmap", "switch_set_floodmap", "switch_set_floodmap"]], [[], [], 1, 3, 0, 0, 0, 2, 0, 1, []], [["\n"], [-3, 1], 2, 7, 3, 1, 3, 0, 0, 1, []], [[], [], 1, 1, 0, 0, 0, 0, 0, 1, []], [[], [], 0, 3, 0, 0, 0, 0, 0, 2, []], [[], [], 2, 6, 1, 0, 1, 0, 0, 2, ["switch_add_portmap"]], [[], [112], 1, 4, 0, 1, 0, 0, 2, 1, []], [[], [], 1, 1, 0, 0, 0, 0, 0, 1, []]], "fname": "add_router"}
{"src": "/home/a123456/Desktop/GetRawFeatures/binaries/asus/asus_RT-AC1200E_3.0.0.4_380_10574-gfd1b439_binary/snooper", "n_num": 13, "succs": [[2, 1], [3], [3], [5, 4], [12], [6], [10, 7], [6, 8], [12, 9], [12], [12, 11], [12], []], "funcaddr": 7980, "keyimportapiinfo": 9, "netkeywords": 0, "casenetkeywords": 0, "features": [[["\n"], [2, -15036, -1592], 9, 15, 0, 3, 0, 0, 0, 2, []], [[], [256, 224], 1, 4, 1, 0, 1, 2, 0, 1, []], [[], [], 0, 1, 0, 0, 0, 0, 0, 1, []], [["\n", "\n"], [32, 60, 1500], 4, 18, 0, 3, 0, 2, 4, 2, ["ether_mtoe", "ether_mtoe", "ether_mtoe", "build_query", "build_query", "build_query"]], [[], [-1], 0, 3, 0, 1, 0, 2, 0, 1, []], [["\n"], [40, 20, 17, 8, 6], 12, 24, 0, 5, 0, 0, 2, 1, ["memset", "memset", "memset"]], [["\n"], [1592], 7, 11, 0, 1, 0, 2, 0, 0, []], [[], [20], 6, 15, 0, 1, 0, 2, 2, 2, ["sendto", "sendto", "sendto", "__errno_location"]], [[], [4], 2, 8, 0, 1, 0, 2, 2, 2, []], [[], [], 1, 3, 0, 0, 0, 0, 0, 2, ["accept_igmp"]], [[], [127], 1, 4, 0, 1, 0, 2, 0, 2, ["strerror"]], [["sendto: %s"], [24840, 3], 4, 14, 0, 2, 0, 2, 4, 1, ["logger", "logger", "logger"]], [[], [-1], 2, 7, 0, 1, 0, 0, 2, 1, []]], "fname": "send_query"}
{"src": "/home/a123456/Desktop/GetRawFeatures/binaries/asus/asus_RT-AC1200E_3.0.0.4_380_10574-gfd1b439_binary/snooper", "n_num": 28, "succs": [[26, 1], [4, 2], [8, 3], [8], [6, 5], [8], [8, 7], [8], [20, 9], [20, 10], [20, 11], [20, 12], [15], [16, 14], [15], [13, 16], [17], [19, 18], [21], [17, 20], [21], [23, 22], [], [24], [26, 25], [27], [27], []], "funcaddr": 22244, "keyimportapiinfo": 9, "netkeywords": 0, "casenetkeywords": 0, "features": [[["\n"], [2, -29300, -184, 2, 1], 12, 24, 0, 5, 0, 2, 2, 2, ["open_socket", "open_socket", "open_socket"]], [["\n", "\n", "\n"], [26900, 32, 36, 56, 40, 24, 8, 35202], 11, 35, 1, 7, 1, 2, 8, 2, ["memset", "memset", "memset", "memset", "memset", "memset", "strncpy", "strncpy", "strncpy", "ioctl", "ioctl", "ioctl"]], [[], [-1], 0, 1, 0, 1, 0, 0, 0, 1, []], [["\n"], [64, 16, 9, 35202], 6, 18, 1, 3, 1, 2, 4, 2, ["strncpy", "strncpy", "strncpy", "ioctl", "ioctl", "ioctl"]], [["vlan%u", "\n"], [25396, 26932, 1], 4, 12, 0, 3, 0, 2, 2, 2, ["sscanf", "sscanf", "sscanf"]], [[], [], 3, 5, 0, 0, 0, 2, 0, 1, []], [["\\x02\n", "\n"], [18836, 2, 32], 2, 12, 0, 3, 0, 2, 2, 2, []], [["eth0"], [25404, 16], 3, 10, 0, 2, 0, 2, 2, 1, ["strncpy", "strncpy", "strncpy"]], [["%16[^.].%u", "\n"], [25412, 26932, 2], 3, 12, 0, 3, 0, 2, 2, 2, ["sscanf", "sscanf", "sscanf"]], [[], [16], 3, 10, 0, 1, 0, 0, 2, 1, ["strncpy", "strncpy", "strncpy"]], [["\n"], [3, 28], 1, 10, 0, 2, 0, 2, 2, 2, []], [[], [], 0, 1, 0, 0, 0, 0, 0, 1, []], [[], [16], 2, 7, 2, 0, 2, 0, 0, 2, []], [["/proc/cpuinfo", "r\n"], [25424, 25440], 4, 11, 0, 2, 0, 0, 2, 2, ["fopen", "fopen", "fopen"]], [["\n"], [92], 2, 5, 0, 1, 0, 2, 0, 1, []], [[], [], 2, 7, 0, 0, 0, 0, 2, 2, ["feof", "feof", "feof"]], [["system type : %63[^\\n]"], [25444, 1], 2, 10, 0, 2, 0, 2, 2, 2, ["fscanf", "fscanf", "fscanf"]], [[], [64], 3, 8, 0, 1, 0, 0, 2, 1, ["fgets", "fgets", "fgets"]], [["\n", "\\xccc@\n"], [8, 92, 25708], 4, 10, 0, 3, 0, 0, 2, 1, ["fclose", "fclose", "fclose", "strstr"]], [["MT7628", "\\xbcc@\n"], [-1, -8], 2, 9, 0, 2, 0, 0, 2, 2, []], [["\\x94c@\n", "\\xc4c@\n"], [3, 25652], 2, 7, 1, 2, 1, 2, 0, 1, []], [[], [], 1, 3, 0, 0, 0, 0, 0, 2, ["strstr"]], [[], [-1], 2, 6, 0, 1, 0, 0, 0, 2, []], [[], [2, 25556], 2, 9, 1, 3, 1, 2, 0, 0, []], [["unsupported switch: %s"], [25468, 3], 8, 20, 0, 2, 0, 2, 6, 1, ["__errno_location", "__errno_location", "__errno_location", "strerror", "strerror", "strerror", "logger", "logger", "logger"]], [[], [], 3, 5, 0, 0, 0, 2, 0, 2, ["close"]], [[], [-1], 1, 7, 0, 1, 0, 2, 2, 1, []], [["\n"], [184], 6, 9, 0, 1, 0, 2, 0, 0, []]], "fname": "switch_init"}
{"src": "/home/a123456/Desktop/GetRawFeatures/binaries/asus/asus_RT-AC1200E_3.0.0.4_380_10574-gfd1b439_binary/snooper", "n_num": 1, "succs": [[]], "funcaddr": 3948, "keyimportapiinfo": 9, "netkeywords": 0, "casenetkeywords": 0, "features": [[["\n", "\\x02\n", "\\x02\n", "\n"], [2, -11004, -32, 2, -11040, 4312, 2, -11080, 23936, 32], 11, 35, 0, 10, 0, 2, 8, 0, []]], "fname": "_init"}
{"src": "/home/a123456/Desktop/GetRawFeatures/binaries/asus/asus_RT-AC1200E_3.0.0.4_380_10574-gfd1b439_binary/snooper", "n_num": 5, "succs": [[3, 1], [3, 2], [4], [4], []], "funcaddr": 12676, "keyimportapiinfo": 9, "netkeywords": 0, "casenetkeywords": 0, "features": [[["\n", "\n"], [2, -19732, -40, 26212, 16, -1], 14, 28, 0, 6, 0, 2, 4, 2, ["memset", "memset", "memset", "now", "now", "now"]], [[], [], 3, 8, 0, 0, 0, 0, 2, 2, ["__errno_location", "__errno_location", "__errno_location"]], [[], [], 0, 1, 0, 0, 0, 0, 0, 1, []], [["timer: %s"], [25324, 3, -1], 5, 16, 0, 3, 0, 2, 4, 1, ["strerror", "strerror", "strerror", "logger", "logger", "logger"]], [["\n"], [40], 3, 6, 0, 1, 0, 2, 0, 0, []]], "fname": "init_timers"}
{"src": "/home/a123456/Desktop/GetRawFeatures/binaries/asus/asus_RT-AC1200E_3.0.0.4_380_10574-gfd1b439_binary/snooper", "n_num": 6, "succs": [[1], [5, 2], [1, 3], [5, 4], [5], []], "funcaddr": 4684, "keyimportapiinfo": 9, "netkeywords": 0, "casenetkeywords": 0, "features": [[["\n", "\n", "\n"], [2, -11740, -88, 40, 1, 20, 17, 144, 6, 32], 23, 39, 0, 10, 0, 0, 2, 1, ["memset", "memset", "memset"]], [[], [20, 6], 6, 15, 0, 2, 0, 2, 2, 2, ["sendto", "sendto", "sendto", "__errno_location"]], [[], [4], 2, 8, 0, 1, 0, 2, 2, 2, []], [["\n"], [88], 5, 9, 0, 1, 0, 2, 0, 0, []], [[], [127], 1, 4, 0, 1, 0, 2, 0, 2, ["strerror"]], [["sendto: %s"], [24840, 3], 4, 12, 0, 2, 0, 0, 4, 1, ["logger", "logger", "logger"]]], "fname": "switch_probe"}
{"src": "/home/a123456/Desktop/GetRawFeatures/binaries/asus/asus_RT-AC1200E_3.0.0.4_380_10574-gfd1b439_binary/snooper", "n_num": 14, "succs": [[6, 1], [3, 2], [13], [5, 4], [12, 5], [13], [11], [9, 8], [10, 9], [10], [11], [7, 12], [13], []], "funcaddr": 14252, "keyimportapiinfo": 9, "netkeywords": 0, "casenetkeywords": 0, "features": [[["\n", "sendto: %s", "\n"], [2, -21308, -40], 8, 18, 0, 4, 0, 0, 2, 2, ["now", "now", "now"]], [["\\x02\n"], [13724], 2, 10, 0, 1, 0, 0, 2, 2, []], [[], [], 2, 4, 0, 0, 0, 2, 0, 1, []], [[], [-1], 0, 3, 0, 1, 0, 2, 0, 1, []], [[], [92], 3, 9, 0, 1, 0, 0, 2, 2, ["timer_pending", "timer_pending", "timer_pending"]], [["\n"], [40], 4, 7, 0, 1, 0, 2, 0, 0, []], [[], [], 1, 5, 0, 1, 0, 2, 0, 2, []], [[], [], 2, 9, 0, 0, 0, 2, 2, 1, ["mod_timer", "mod_timer", "mod_timer"]], [[], [], 0, 1, 0, 0, 0, 0, 0, 1, []], [[], [92], 1, 5, 0, 1, 0, 0, 0, 2, ["timer_pending"]], [[], [], 3, 9, 0, 0, 0, 0, 2, 2, ["mod_timer"]], [[], [], 1, 5, 0, 1, 0, 2, 0, 2, []], [[], [], 1, 4, 0, 0, 0, 0, 2, 1, []], [[], [], 1, 1, 0, 0, 0, 0, 0, 1, []]], "fname": "expire_members"}
{"src": "/home/a123456/Desktop/GetRawFeatures/binaries/asus/asus_RT-AC1200E_3.0.0.4_380_10574-gfd1b439_binary/snooper", "n_num": 10, "succs": [[2, 1], [9], [7, 3], [4], [6, 5], [6], [4, 7], [9, 8], [9], []], "funcaddr": 12464, "keyimportapiinfo": 9, "netkeywords": 0, "casenetkeywords": 0, "features": [[["\n"], [2, -19520, -40], 7, 13, 0, 3, 0, 0, 0, 2, []], [[], [-1], 0, 3, 0, 1, 0, 2, 0, 1, []], [["\n"], [26212, 32767], 3, 7, 0, 2, 0, 2, 0, 2, []], [["\n"], [40], 3, 7, 0, 1, 0, 2, 0, 0, []], [[], [65535], 1, 4, 1, 1, 1, 0, 0, 1, []], [[], [], 4, 11, 0, 1, 0, 0, 2, 2, ["now", "now", "now"]], [[], [], 2, 6, 0, 1, 0, 2, 0, 2, []], [[], [], 1, 1, 0, 0, 0, 0, 0, 1, []], [[], [], 1, 4, 0, 0, 0, 0, 0, 2, []], [[], [], 2, 6, 0, 0, 0, 0, 2, 1, ["time_to_timeval", "time_to_timeval", "time_to_timeval"]]], "fname": "next_timer"}
{"src": "/home/a123456/Desktop/GetRawFeatures/binaries/asus/asus_RT-AC1200E_3.0.0.4_380_10574-gfd1b439_binary/snooper", "n_num": 3, "succs": [[2, 1], [2], []], "funcaddr": 8520, "keyimportapiinfo": 9, "netkeywords": 0, "casenetkeywords": 0, "features": [[["\n", "\n", "\\x02\n", "\n"], [2, -15576, -40, -2, 26176, 2, 8744, 26192, 1], 16, 33, 3, 8, 3, 0, 2, 2, ["set_timer", "set_timer", "set_timer"]], [["\n"], [26192, 1], 4, 11, 0, 2, 0, 0, 4, 1, ["now", "now", "now", "mod_timer", "mod_timer", "mod_timer"]], [["\n"], [256, 224, -1, 7, 24, 24, 31, 40], 7, 18, 5, 2, 5, 2, 2, 0, ["listen_query", "listen_query", "listen_query"]]], "fname": "init_querier"}
{"src": "/home/a123456/Desktop/GetRawFeatures/binaries/asus/asus_RT-AC1200E_3.0.0.4_380_10574-gfd1b439_binary/snooper", "n_num": 8, "succs": [[6, 1], [4], [7, 3], [4], [2, 5], [6], [7], []], "funcaddr": 11492, "keyimportapiinfo": 9, "netkeywords": 0, "casenetkeywords": 0, "features": [[["\n"], [2, -18548, -32], 8, 16, 0, 3, 0, 0, 2, 2, ["timer_pending", "timer_pending", "timer_pending"]], [[], [], 2, 4, 0, 0, 0, 2, 0, 1, []], [[], [], 1, 1, 0, 0, 0, 0, 0, 1, []], [[], [], 0, 3, 0, 0, 0, 0, 0, 2, []], [[], [], 1, 3, 0, 0, 0, 2, 0, 2, []], [[], [], 1, 1, 0, 0, 0, 0, 0, 1, []], [["\n"], [32], 1, 4, 0, 1, 0, 2, 0, 0, []], [[], [], 2, 2, 0, 0, 0, 0, 0, 1, []]], "fname": "set_timer"}
{"src": "/home/a123456/Desktop/GetRawFeatures/binaries/asus/asus_RT-AC1200E_3.0.0.4_380_10574-gfd1b439_binary/snooper", "n_num": 4, "succs": [[2, 1], [3], [3], []], "funcaddr": 12112, "keyimportapiinfo": 9, "netkeywords": 0, "casenetkeywords": 0, "features": [[["\n", "\n"], [2, -19168, -40, 1, 24], 5, 14, 0, 5, 0, 2, 2, 2, ["clock_gettime", "clock_gettime", "clock_gettime"]], [[], [-1], 0, 3, 0, 1, 0, 2, 0, 1, []], [[], [17179, 56963, 2, 7, 18, 31, 3], 3, 15, 6, 5, 6, 0, 0, 1, []], [["\n"], [40], 1, 4, 0, 1, 0, 2, 0, 0, []]], "fname": "now"}
{"src": "/home/a123456/Desktop/GetRawFeatures/binaries/asus/asus_RT-AC1200E_3.0.0.4_380_10574-gfd1b439_binary/snooper", "n_num": 34, "succs": [[31, 1], [32, 2], [32, 3], [21, 4], [9, 5], [9, 6], [11, 7], [31, 8], [14], [31, 10], [13], [31, 12], [13], [30], [19], [32, 16], [18, 17], [], [19], [15, 20], [33], [24, 22], [26, 23], [29], [32, 25], [27, 26], [28], [28], [29], [30], [32], [32], [33], []], "funcaddr": 10092, "keyimportapiinfo": 9, "netkeywords": 0, "casenetkeywords": 0, "features": [[["\n", "(\n"], [2, -17148, -72, -20], 12, 23, 0, 5, 0, 0, 0, 2, []], [[], [2], 1, 5, 0, 1, 0, 2, 0, 2, []], [[], [], 0, 1, 0, 0, 0, 0, 0, 1, []], [[], [255, 8, 8, 15, 2], 1, 18, 6, 3, 6, 0, 0, 2, []], [[], [], 1, 1, 0, 0, 0, 0, 0, 1, []], [[], [17, 18], 1, 5, 0, 2, 0, 2, 0, 2, []], [[], [22], 0, 3, 0, 1, 0, 2, 0, 2, []], [[], [8], 0, 4, 0, 1, 0, 2, 0, 2, []], [[], [23], 0, 3, 0, 1, 0, 2, 0, 2, []], [[], [8], 1, 4, 0, 1, 0, 2, 0, 2, []], [[], [34], 0, 3, 0, 1, 0, 2, 0, 2, []], [[], [], 0, 3, 0, 0, 0, 2, 0, 2, []], [[], [8], 1, 4, 0, 1, 0, 2, 0, 2, []], [[], [], 1, 3, 0, 0, 0, 2, 0, 1, []], [["%\\x90C\n", "\\x02\n", "\\x02\n"], [8, -8, 9436, 8, 9124], 3, 11, 2, 4, 2, 2, 0, 1, []], [["8\n"], [9436], 2, 7, 0, 1, 0, 2, 0, 1, []], [[], [], 1, 6, 0, 0, 0, 2, 2, 1, []], [["\\x18\n"], [9124], 2, 3, 0, 1, 0, 0, 0, 1, []], [[], [1], 0, 3, 0, 1, 0, 2, 0, 1, []], [[], [-1, -1, 1], 0, 5, 0, 3, 0, 2, 0, 2, []], [[], [1], 0, 4, 0, 1, 0, 0, 0, 2, []], [[], [-1, 255, 8], 3, 10, 3, 1, 3, 0, 0, 2, []], [[], [2, 25280], 2, 9, 1, 3, 1, 2, 0, 0, []], [[], [8, 2], 1, 5, 1, 3, 1, 0, 0, 1, []], [[], [], 1, 3, 0, 0, 0, 2, 0, 1, []], [["\n"], [72], 9, 12, 0, 1, 0, 2, 0, 0, []], [[], [10000], 1, 4, 0, 1, 0, 0, 0, 2, []], [[], [], 0, 4, 0, 0, 0, 0, 0, 2, []], [[], [], 1, 3, 0, 0, 0, 2, 0, 1, []], [[], [2, 7], 0, 6, 2, 2, 2, 2, 0, 1, []], [[], [], 4, 7, 0, 0, 0, 0, 2, 1, ["accept_query", "accept_query", "accept_query"]], [[], [24, 24], 1, 6, 2, 0, 2, 2, 0, 2, []], [[], [4, 15, 7, 3, 16, 2, 7], 0, 10, 7, 3, 7, 0, 0, 1, []], [[], [26214, 3, 26215, 31, 2], 2, 9, 4, 2, 4, 0, 0, 1, []]], "fname": "accept_igmp"}
{"src": "/home/a123456/Desktop/GetRawFeatures/binaries/asus/asus_RT-AC1200E_3.0.0.4_380_10574-gfd1b439_binary/snooper", "n_num": 10, "succs": [[8, 1], [3, 2], [4, 3], [7], [6, 5], [9, 6], [7], [9], [9], []], "funcaddr": 18460, "keyimportapiinfo": 9, "netkeywords": 0, "casenetkeywords": 0, "features": [[["\n"], [2, -25516, -32], 6, 15, 0, 3, 0, 2, 2, 2, ["socket", "socket", "socket"]], [[], [1], 2, 9, 0, 1, 0, 2, 2, 2, ["fcntl", "fcntl", "fcntl"]], [["socket: %s"], [-1, 25384, 3], 8, 18, 0, 3, 0, 0, 6, 1, ["__errno_location", "__errno_location", "__errno_location", "strerror", "strerror", "strerror", "logger", "logger", "logger"]], [[], [1, 2], 2, 9, 1, 1, 1, 2, 2, 2, ["fcntl", "fcntl", "fcntl"]], [["fcntl::FD_CLOEXEC: %s"], [25336], 7, 15, 0, 1, 0, 2, 4, 1, ["__errno_location", "__errno_location", "__errno_location", "strerror", "strerror", "strerror", "logger"]], [[], [3], 2, 9, 0, 1, 0, 2, 2, 2, ["fcntl", "fcntl", "fcntl"]], [[], [3, -1], 3, 13, 0, 2, 0, 2, 4, 1, ["close", "close", "close"]], [[], [128, 4], 2, 9, 1, 1, 1, 2, 2, 2, ["fcntl", "fcntl", "fcntl"]], [["fcntl::O_NONBLOCK: %s"], [25360], 7, 13, 0, 1, 0, 0, 4, 1, ["__errno_location", "__errno_location", "__errno_location", "strerror", "strerror", "strerror", "logger"]], [["\n"], [32], 2, 6, 0, 1, 0, 2, 0, 0, []]], "fname": "open_socket"}
{"src": "/home/a123456/Desktop/GetRawFeatures/binaries/asus/asus_RT-AC1200E_3.0.0.4_380_10574-gfd1b439_binary/snooper", "n_num": 21, "succs": [[2, 1], [18], [4, 3], [14], [6, 5], [6], [11, 7], [14, 8], [10, 9], [15, 10], [14], [14, 12], [15, 13], [14], [15], [19, 16], [20, 17], [18], [19], [20], []], "funcaddr": 16244, "keyimportapiinfo": 9, "netkeywords": 0, "casenetkeywords": 0, "features": [[["\n"], [2, -23300, -56], 9, 19, 0, 3, 0, 0, 0, 2, []], [[], [-1], 0, 3, 0, 1, 0, 2, 0, 1, []], [["\\x02\n"], [13724], 2, 9, 0, 1, 0, 0, 2, 2, []], [[], [], 0, 1, 0, 0, 0, 0, 0, 1, []], [[], [], 0, 3, 0, 0, 0, 2, 0, 1, []], [["\\x02\n"], [15376], 3, 12, 0, 1, 0, 0, 2, 2, []], [[], [], 1, 1, 0, 0, 0, 0, 0, 1, []], [["\\x02\n"], [12876], 2, 6, 0, 1, 0, 0, 2, 1, []], [["!\\x18\n"], [13124], 1, 4, 0, 1, 0, 0, 0, 2, []], [[], [], 1, 8, 1, 0, 1, 0, 2, 2, []], [[], [], 2, 10, 1, 0, 1, 0, 2, 2, []], [[], [92], 4, 13, 0, 2, 0, 0, 4, 2, ["now", "now", "now", "timer_pending", "timer_pending", "timer_pending"]], [[], [], 2, 5, 0, 1, 0, 2, 0, 2, []], [[], [], 2, 8, 0, 0, 0, 2, 2, 1, ["mod_timer", "mod_timer", "mod_timer"]], [[], [], 1, 6, 1, 0, 1, 0, 0, 2, []], [[], [], 1, 3, 0, 0, 0, 0, 0, 2, []], [["\\x02\n"], [13180], 2, 6, 0, 1, 0, 0, 2, 1, []], [[], [], 1, 3, 0, 0, 0, 0, 0, 2, []], [[], [], 1, 1, 0, 0, 0, 0, 0, 1, []], [[], [], 2, 6, 0, 0, 0, 0, 2, 1, ["switch_del_portmap", "switch_del_portmap", "switch_del_portmap"]], [["\n"], [56], 6, 9, 0, 1, 0, 2, 0, 0, []]], "fname": "del_member"}
{"src": "/home/a123456/Desktop/GetRawFeatures/binaries/asus/asus_RT-AC1200E_3.0.0.4_380_10574-gfd1b439_binary/snooper", "n_num": 14, "succs": [[12, 1], [9, 2], [13], [5, 4], [6], [6], [7], [12, 8], [10], [10], [3, 11], [7], [13], []], "funcaddr": 12240, "keyimportapiinfo": 9, "netkeywords": 0, "casenetkeywords": 0, "features": [[["\n", "\n"], [2, -19296, -40, 26212], 10, 20, 0, 4, 0, 0, 2, 2, ["now", "now", "now"]], [[], [], 1, 5, 0, 1, 0, 2, 0, 2, []], [[], [], 1, 1, 0, 0, 0, 0, 0, 1, []], [[], [], 1, 3, 0, 0, 0, 2, 0, 1, []], [[], [], 1, 1, 0, 0, 0, 0, 0, 1, []], [["\n"], [40], 2, 6, 0, 1, 0, 2, 0, 0, []], [[], [], 1, 3, 0, 0, 0, 0, 0, 2, []], [[], [], 1, 3, 0, 0, 0, 2, 0, 1, []], [[], [], 1, 1, 0, 0, 0, 0, 0, 1, []], [[], [], 8, 11, 0, 0, 0, 0, 2, 1, []], [[], [], 0, 3, 0, 0, 0, 0, 0, 2, []], [[], [], 1, 3, 0, 0, 0, 2, 0, 1, []], [[], [], 2, 5, 0, 1, 0, 2, 0, 2, []], [[], [], 0, 3, 0, 0, 0, 2, 0, 1, []]], "fname": "run_timers"}
{"src": "/home/a123456/Desktop/GetRawFeatures/binaries/asus/asus_RT-AC1200E_3.0.0.4_380_10574-gfd1b439_binary/snooper", "n_num": 5, "succs": [[1], [1, 2], [4, 3], [4], []], "funcaddr": 15028, "keyimportapiinfo": 9, "netkeywords": 0, "casenetkeywords": 0, "features": [[["\n", "\n", "\n", "\n", "\n"], [2, -22084, -48, 26228, 268, 26496, 26508, 268, 26776, 120], 27, 49, 0, 10, 0, 0, 6, 1, ["memset", "memset", "memset", "memset", "memset", "memset", "memset", "memset", "memset"]], [["\n", "\n"], [4, 256], 2, 8, 0, 4, 0, 2, 0, 2, []], [["X\n", "\n", "\n", "\\x02\n", "\n", "\n"], [12960, 26776, 26868, 14544, 26776, 26888], 10, 25, 0, 6, 0, 0, 6, 2, ["set_timer", "set_timer", "set_timer", "switch_set_floodmap", "switch_set_floodmap", "switch_set_floodmap"]], [[], [3], 3, 4, 1, 0, 1, 0, 0, 1, []], [["\n"], [48], 6, 10, 0, 1, 0, 2, 0, 0, []]], "fname": "init_cache"}
{"src": "/home/a123456/Desktop/GetRawFeatures/binaries/asus/asus_RT-AC1200E_3.0.0.4_380_10574-gfd1b439_binary/snooper", "n_num": 3, "succs": [[2, 1], [2], []], "funcaddr": 20588, "keyimportapiinfo": 9, "netkeywords": 0, "casenetkeywords": 0, "features": [[["\n"], [2, -27644, -48], 8, 14, 0, 3, 0, 2, 0, 2, []], [["\n", "\\x03\n", "\\x02\n"], [24, 19592, 19688], 7, 18, 0, 3, 0, 0, 4, 1, []], [["\n"], [48], 4, 7, 0, 1, 0, 2, 0, 0, []]], "fname": "0040506c"}
{"src": "/home/a123456/Desktop/GetRawFeatures/binaries/asus/asus_RT-AC1200E_3.0.0.4_380_10574-gfd1b439_binary/snooper", "n_num": 47, "succs": [[42, 1], [4, 2], [20, 3], [46], [43], [6], [42, 7], [14, 8], [14, 9], [15, 10], [42, 11], [42, 12], [15, 13], [46, 14], [15], [42, 16], [18, 17], [6, 18], [42, 19], [5], [22, 21], [23], [23], [44], [25], [42, 26], [39, 27], [37, 28], [42, 29], [35, 30], [42, 31], [42, 32], [35, 33], [36, 34], [46, 35], [36], [37], [42, 38], [41, 39], [25, 40], [41], [44, 42], [45], [5], [24], [46], []], "funcaddr": 19688, "keyimportapiinfo": 9, "netkeywords": 0, "casenetkeywords": 0, "features": [[["\n"], [2, -26744, -88], 14, 22, 0, 3, 0, 0, 0, 2, []], [[], [1, 38], 1, 6, 2, 1, 2, 0, 0, 2, []], [[], [-1], 0, 3, 0, 1, 0, 2, 0, 1, []], [[], [24, -1], 0, 4, 1, 1, 1, 0, 0, 2, []], [["\\x02\n", "\n", "\\x02\n", "\n", "\n"], [36, 19212, 1, 24, 19368, 28, 32], 2, 15, 0, 7, 0, 2, 2, 1, []], [[], [], 0, 3, 0, 0, 0, 2, 0, 1, []], [[], [], 1, 3, 0, 0, 0, 0, 0, 2, []], [["\n"], [88], 10, 13, 0, 1, 0, 2, 0, 0, []], [[], [], 0, 3, 0, 0, 0, 2, 0, 1, []], [[], [], 1, 1, 0, 0, 0, 0, 0, 1, ["usleep"]], [[], [500, 40, 4], 1, 12, 0, 3, 0, 2, 4, 2, []], [[], [1, 12], 1, 5, 2, 0, 2, 0, 0, 2, []], [[], [112, 127], 0, 4, 2, 0, 2, 0, 0, 2, []], [[], [], 1, 1, 0, 0, 0, 0, 0, 1, []], [[], [7, 15], 1, 5, 2, 0, 2, 2, 0, 2, []], [[], [48, 4], 1, 9, 0, 2, 0, 2, 2, 2, []], [[], [2, 1], 0, 4, 2, 0, 2, 0, 0, 2, []], [[], [44, 4], 1, 9, 0, 2, 0, 2, 2, 2, []], [[], [], 3, 5, 0, 0, 0, 2, 0, 2, []], [[], [], 2, 5, 0, 0, 0, 2, 0, 2, []], [[], [1], 0, 3, 0, 1, 0, 0, 0, 2, []], [[], [20], 1, 4, 0, 1, 0, 2, 0, 2, ["usleep"]], [["\\x02\n"], [36, 19212, 2, 1, 1024], 2, 11, 0, 5, 0, 2, 2, 2, []], [[], [], 0, 3, 0, 0, 0, 2, 0, 1, []], [[], [34308], 0, 3, 1, 0, 1, 2, 0, 1, []], [[], [120, 19212, 4095, 35332], 1, 7, 2, 2, 2, 0, 2, 1, []], [["\\x02\n", "\\x02\n", "\n", "\n", "\n"], [128, 19212, 1, 19368, 28, 24, 32], 4, 18, 0, 7, 0, 2, 2, 1, []], [[], [], 0, 3, 0, 0, 0, 2, 0, 1, []], [[], [], 1, 1, 0, 0, 0, 0, 0, 1, ["usleep"]], [[], [500, 128, 4], 2, 12, 0, 3, 0, 2, 4, 2, []], [[], [32768, 8192], 1, 5, 2, 0, 2, 0, 0, 2, []], [[], [16384], 0, 3, 1, 0, 1, 0, 0, 2, []], [[], [1, 20], 1, 5, 0, 2, 0, 2, 0, 2, ["usleep"]], [[], [140, 4], 1, 9, 0, 2, 0, 2, 2, 2, []], [[], [8192], 0, 3, 1, 0, 1, 0, 0, 2, []], [[], [24, 4, 255], 1, 6, 3, 0, 3, 0, 0, 2, []], [[], [132, 4], 1, 9, 0, 2, 0, 2, 2, 2, []], [[], [], 1, 1, 0, 0, 0, 0, 0, 1, []], [[], [136, 4], 1, 9, 0, 2, 0, 2, 2, 2, []], [[], [16, 4095], 2, 6, 2, 0, 2, 2, 0, 2, []], [[], [], 3, 5, 0, 0, 0, 2, 0, 2, []], [[], [], 1, 4, 0, 0, 0, 2, 0, 2, []], [[], [16384], 0, 1, 1, 0, 1, 0, 0, 1, []], [[], [], 1, 3, 0, 0, 0, 0, 0, 2, []], [[], [128, 19212, 1, 2048], 1, 10, 0, 4, 0, 2, 2, 2, []], [[], [], 1, 1, 0, 0, 0, 0, 0, 1, []], [[], [], 0, 1, 0, 0, 0, 0, 0, 1, []]], "fname": "00404ce8"}
{"src": "/home/a123456/Desktop/GetRawFeatures/binaries/asus/asus_RT-AC1200E_3.0.0.4_380_10574-gfd1b439_binary/snooper", "n_num": 3, "succs": [[1], [1, 2], []], "funcaddr": 13180, "keyimportapiinfo": 9, "netkeywords": 0, "casenetkeywords": 0, "features": [[["\n", "\\x02\n"], [2, -20236, -40, 92, 13000], 10, 19, 0, 5, 0, 0, 2, 1, ["del_timer", "del_timer", "del_timer"]], [[], [1, 9], 1, 10, 0, 2, 0, 2, 2, 2, []], [["\n"], [40], 4, 7, 0, 1, 0, 2, 0, 0, []]], "fname": "0040337c"}
{"src": "/home/a123456/Desktop/GetRawFeatures/binaries/asus/asus_RT-AC1200E_3.0.0.4_380_10574-gfd1b439_binary/snooper", "n_num": 25, "succs": [[3], [24, 2], [3], [1, 4], [24, 5], [8, 6], [8, 7], [21], [11], [13, 10], [11], [9, 12], [24], [15, 14], [15], [18, 16], [20, 17], [20], [20, 19], [20], [21], [23, 22], [23], [24], []], "funcaddr": 13724, "keyimportapiinfo": 9, "netkeywords": 0, "casenetkeywords": 0, "features": [[["\n", "\n", "\n"], [2, -20780, -48, 63, 2, 26516], 11, 24, 2, 5, 2, 2, 2, 1, ["ether_hash", "ether_hash", "ether_hash"]], [[], [112, 6], 1, 6, 0, 2, 0, 0, 0, 2, ["memcmp"]], [[], [], 1, 6, 0, 0, 0, 0, 2, 2, []], [[], [], 1, 1, 0, 0, 0, 0, 0, 1, []], [["\n"], [48], 5, 9, 0, 1, 0, 2, 0, 0, []], [[], [], 1, 3, 0, 0, 0, 0, 0, 2, []], [["\n"], [26508], 2, 6, 0, 1, 0, 0, 0, 2, ["calloc"]], [[], [1, 120], 1, 8, 0, 2, 0, 0, 2, 2, []], [[], [], 2, 5, 0, 0, 0, 2, 0, 1, []], [[], [1], 2, 6, 0, 1, 0, 2, 0, 1, []], [["X\n", "\\x02\n"], [12960, 17784, 92, 112], 14, 26, 0, 4, 0, 0, 4, 2, ["set_timer", "set_timer", "set_timer"]], [[], [], 0, 3, 0, 0, 0, 0, 0, 2, []], [[], [], 1, 4, 0, 0, 0, 0, 0, 2, []], [[], [], 1, 2, 0, 0, 0, 0, 0, 1, []], [[], [], 1, 4, 0, 0, 0, 0, 0, 2, []], [[], [], 0, 3, 0, 0, 0, 2, 0, 1, []], [[], [], 2, 2, 0, 0, 0, 0, 0, 1, []], [[], [], 3, 5, 0, 0, 0, 0, 0, 2, []], [[], [], 3, 5, 0, 0, 0, 0, 0, 2, []], [[], [], 4, 6, 0, 0, 0, 0, 0, 2, []], [[], [], 2, 4, 0, 0, 0, 2, 0, 1, []], [[], [112], 2, 5, 0, 1, 0, 0, 2, 1, ["switch_clr_portmap", "switch_clr_portmap", "switch_clr_portmap"]], [["\n"], [26508], 1, 2, 0, 1, 0, 0, 0, 1, []], [[], [4], 2, 3, 0, 1, 0, 0, 0, 1, []], [["\n"], [26508], 7, 8, 0, 1, 0, 0, 0, 1, []]], "fname": "0040359c"}
{"src": "/home/a123456/Desktop/GetRawFeatures/binaries/asus/asus_RT-AC1200E_3.0.0.4_380_10574-gfd1b439_binary/snooper", "n_num": 29, "succs": [[3], [28, 2], [3], [1, 4], [27, 5], [17, 6], [7], [15, 8], [14], [13, 10], [12, 11], [12], [24], [14], [9, 15], [7, 16], [17], [21, 18], [20, 19], [20], [24], [28, 22], [27, 23], [24], [26, 25], [26], [27], [28], []], "funcaddr": 15376, "keyimportapiinfo": 9, "netkeywords": 0, "casenetkeywords": 0, "features": [[["\n"], [2, -22432, -48, 2], 9, 19, 1, 4, 1, 2, 0, 1, []], [[], [], 0, 3, 0, 0, 0, 0, 0, 2, []], [[], [], 1, 4, 0, 0, 0, 2, 0, 2, []], [[], [], 1, 1, 0, 0, 0, 0, 0, 1, []], [["\n"], [48], 6, 9, 0, 1, 0, 2, 0, 0, []], [[], [2], 0, 3, 0, 1, 0, 0, 0, 2, []], [[], [], 1, 3, 0, 0, 0, 2, 0, 2, []], [[], [], 0, 1, 0, 0, 0, 0, 0, 1, []], [[], [], 0, 2, 0, 0, 0, 0, 0, 1, []], [["\n"], [26496], 1, 4, 0, 1, 0, 0, 0, 2, []], [[], [], 0, 3, 0, 0, 0, 2, 0, 2, []], [[], [], 1, 3, 0, 0, 0, 2, 0, 1, []], [[], [1, 9, 4], 0, 5, 0, 3, 0, 2, 0, 2, []], [[], [], 0, 3, 0, 0, 0, 0, 0, 2, []], [[], [], 2, 4, 0, 0, 0, 2, 0, 2, []], [[], [], 0, 3, 0, 0, 0, 0, 0, 2, []], [[], [], 0, 1, 0, 0, 0, 0, 0, 1, []], [[], [], 2, 2, 0, 0, 0, 0, 0, 1, []], [[], [], 3, 5, 0, 0, 0, 2, 0, 1, []], [[], [2], 3, 7, 1, 1, 1, 0, 0, 2, []], [[], [], 1, 1, 0, 0, 0, 0, 0, 1, []], [[], [], 1, 4, 0, 0, 0, 0, 0, 2, []], [[], [], 1, 5, 0, 0, 0, 0, 0, 2, []], [[], [], 2, 2, 0, 0, 0, 0, 0, 1, []], [[], [16], 5, 12, 0, 1, 0, 2, 2, 1, ["memset", "memset", "memset"]], [[], [1, 16], 2, 9, 0, 2, 0, 0, 2, 2, ["calloc", "calloc", "calloc"]], [[], [1], 2, 4, 0, 1, 0, 0, 0, 1, []], [[], [], 2, 2, 0, 0, 0, 0, 0, 1, []], [[], [12], 2, 4, 0, 2, 0, 0, 0, 1, []]], "fname": "00403c10"}
{"src": "/home/a123456/Desktop/GetRawFeatures/binaries/asus/asus_RT-AC1200E_3.0.0.4_380_10574-gfd1b439_binary/snooper", "n_num": 14, "succs": [[12, 1], [4, 2], [7, 3], [13], [6, 5], [6], [11], [9, 8], [10], [10], [11], [12], [13], []], "funcaddr": 20928, "keyimportapiinfo": 9, "netkeywords": 0, "casenetkeywords": 0, "features": [[["\n"], [2, -27984, -48], 9, 18, 0, 3, 0, 0, 0, 2, []], [[], [1, 38, 15], 0, 6, 3, 1, 3, 0, 0, 2, []], [[], [], 1, 1, 0, 0, 0, 0, 0, 1, []], [[], [24], 1, 4, 1, 0, 1, 0, 0, 2, []], [[], [7, 1], 0, 4, 2, 0, 2, 2, 0, 2, []], [[], [], 1, 3, 0, 0, 0, 2, 0, 1, []], [["\\x02\n"], [19212, 116, 4095, 16, 32768, 120], 3, 18, 4, 3, 4, 2, 4, 2, []], [["\n"], [-1, 48], 4, 8, 0, 2, 0, 2, 0, 0, []], [[], [127, 12, 112], 0, 4, 4, 0, 4, 0, 0, 1, []], [["\\x02\n"], [19212, 60, 56, 52, 52, 2, 2], 4, 23, 0, 7, 0, 2, 6, 1, []], [["\\x02\n"], [20736], 2, 6, 0, 1, 0, 0, 2, 1, []], [[], [], 0, 3, 0, 0, 0, 2, 0, 1, []], [[], [255, 65280, 4, 12], 1, 5, 4, 0, 4, 0, 0, 1, []], [["\\x02\n"], [19212, 124, 128, 32769, 128, 32768], 2, 15, 2, 4, 2, 0, 4, 1, []]], "fname": "004051c0"}
{"src": "/home/a123456/Desktop/GetRawFeatures/binaries/asus/asus_RT-AC1200E_3.0.0.4_380_10574-gfd1b439_binary/snooper", "n_num": 6, "succs": [[1], [3, 2], [5], [1, 4], [5], []], "funcaddr": 8928, "keyimportapiinfo": 9, "netkeywords": 0, "casenetkeywords": 0, "features": [[["\n", "\\xe0\n", "\n", "\n", "timer: %s"], [2, -15984, -64, 25300, 24, 30, 24], 10, 18, 0, 7, 0, 0, 0, 1, ["ether_mtoe"]], [[], [6, 8], 7, 22, 1, 2, 1, 0, 6, 2, ["ether_mtoe", "ether_mtoe", "ether_mtoe", "memcmp", "memcmp", "memcmp"]], [[], [1], 0, 3, 0, 1, 0, 2, 0, 1, []], [[], [], 1, 3, 0, 0, 0, 2, 0, 2, ["ether_mtoe"]], [["\n"], [64], 6, 9, 0, 1, 0, 2, 0, 0, []], [[], [], 0, 1, 0, 0, 0, 0, 0, 1, []]], "fname": "004022e0"}
{"src": "/home/a123456/Desktop/GetRawFeatures/binaries/asus/asus_RT-AC1200E_3.0.0.4_380_10574-gfd1b439_binary/snooper", "n_num": 6, "succs": [[2, 1], [2], [5, 3], [5, 4], [5], []], "funcaddr": 18836, "keyimportapiinfo": 9, "netkeywords": 0, "casenetkeywords": 0, "features": [[["\n", "\n"], [2, -25892, -80, 24, 28], 12, 27, 0, 5, 0, 0, 2, 2, ["memset", "memset", "memset"]], [[], [], 2, 2, 0, 0, 0, 0, 0, 1, []], [["\\xf3\\x89\n", "\n"], [2, 25604, 26900], 8, 17, 1, 3, 1, 2, 2, 2, ["ioctl", "ioctl", "ioctl"]], [[], [], 1, 3, 0, 0, 0, 0, 0, 2, []], [["\n"], [80], 6, 10, 0, 1, 0, 2, 0, 0, []], [[], [], 1, 1, 0, 0, 0, 0, 0, 1, []]], "fname": "00404994"}
{"src": "/home/a123456/Desktop/GetRawFeatures/binaries/asus/asus_RT-AC1200E_3.0.0.4_380_10574-gfd1b439_binary/snooper", "n_num": 7, "succs": [[5, 1], [6, 2], [5, 3], [5, 4], [6], [6], []], "funcaddr": 9436, "keyimportapiinfo": 9, "netkeywords": 0, "casenetkeywords": 0, "features": [[["\n"], [2, -16492, -56], 7, 15, 0, 3, 0, 0, 0, 2, []], [[], [61440, 24, 57344], 2, 7, 2, 0, 2, 2, 0, 2, []], [[], [], 0, 1, 0, 0, 0, 0, 0, 1, []], [["\\x02\n"], [8928], 2, 8, 0, 1, 0, 0, 2, 2, []], [["\n"], [56], 5, 8, 0, 1, 0, 2, 0, 0, []], [[], [], 2, 8, 0, 0, 0, 2, 2, 2, ["get_port", "get_port", "get_port"]], [["\n"], [24, 3, 63392, 1], 5, 19, 1, 2, 1, 2, 4, 1, ["ether_mtoe", "ether_mtoe", "ether_mtoe", "add_member", "add_member", "add_member"]]], "fname": "004024dc"}
{"src": "/home/a123456/Desktop/GetRawFeatures/binaries/asus/asus_RT-AC1200E_3.0.0.4_380_10574-gfd1b439_binary/snooper", "n_num": 9, "succs": [[8, 1], [5, 2], [7, 3], [6, 4], [8], [6], [8], [8], []], "funcaddr": 19212, "keyimportapiinfo": 9, "netkeywords": 0, "casenetkeywords": 0, "features": [[["\n"], [2, -26268, -40, -1], 6, 12, 0, 4, 0, 0, 0, 2, []], [[], [], 1, 4, 0, 0, 0, 0, 0, 2, []], [["\n"], [40], 1, 4, 0, 1, 0, 2, 0, 0, []], [[], [4, 5], 0, 4, 0, 2, 0, 2, 0, 2, []], [[], [], 0, 1, 0, 0, 0, 0, 0, 1, []], [[], [], 0, 3, 0, 0, 0, 2, 0, 2, []], [["\\x02\n", "\n"], [31, 1, 18836, 24], 2, 9, 0, 4, 0, 0, 2, 1, []], [[], [-1], 0, 3, 0, 1, 0, 2, 0, 1, []], [["\n"], [24, 19052, 1], 1, 8, 0, 3, 0, 2, 2, 1, []]], "fname": "00404b0c"}
{"src": "/home/a123456/Desktop/GetRawFeatures/binaries/asus/asus_RT-AC1200E_3.0.0.4_380_10574-gfd1b439_binary/snooper", "n_num": 10, "succs": [[4, 1], [5, 2], [6, 3], [5, 4], [9], [7], [7], [9, 8], [9], []], "funcaddr": 19368, "keyimportapiinfo": 9, "netkeywords": 0, "casenetkeywords": 0, "features": [[["\n"], [2, -26424, -48], 8, 15, 0, 3, 0, 0, 0, 2, []], [[], [], 1, 4, 0, 0, 0, 0, 0, 2, []], [[], [-1], 0, 3, 0, 1, 0, 2, 0, 1, []], [[], [4, 5], 0, 4, 0, 2, 0, 2, 0, 2, []], [["\n"], [24, 19052], 1, 9, 0, 2, 0, 2, 2, 1, []], [[], [], 0, 3, 0, 0, 0, 2, 0, 2, []], [["\\x02\n", "\n"], [31, 18836, 24], 2, 9, 0, 3, 0, 0, 2, 1, []], [["\n"], [48], 4, 8, 0, 1, 0, 2, 0, 0, []], [[], [], 0, 3, 0, 0, 0, 0, 0, 2, []], [["\n"], [24], 2, 7, 0, 1, 0, 0, 2, 1, ["memcpy", "memcpy", "memcpy"]]], "fname": "00404ba8"}
{"src": "/home/a123456/Desktop/GetRawFeatures/binaries/asus/asus_RT-AC1200E_3.0.0.4_380_10574-gfd1b439_binary/snooper", "n_num": 6, "succs": [[1], [5, 2], [5, 3], [1, 4], [5], []], "funcaddr": 20736, "keyimportapiinfo": 9, "netkeywords": 0, "casenetkeywords": 0, "features": [[["\n", "\\x02\n", "\n"], [2, -27792, -64, 19368, 24], 10, 19, 0, 5, 0, 0, 0, 1, []], [[], [4, 500, 1], 2, 12, 0, 3, 0, 2, 2, 2, ["usleep"]], [[], [], 1, 5, 1, 0, 1, 2, 0, 2, []], [["\n"], [64], 7, 10, 0, 1, 0, 2, 0, 0, []], [[], [20], 1, 7, 0, 1, 0, 2, 2, 2, []], [[], [1], 0, 1, 0, 1, 0, 0, 0, 1, []]], "fname": "00405100"}
